<?xml version="1.0" encoding="utf-8"?>
<TFuelModuleDescriptors>
  <TFuelModuleDescriptor id="23720">
    <ControllerName>FuelController</ControllerName>
    <FuelCapacity>500</FuelCapacity>
    <FuelMoveDuration>750</FuelMoveDuration>
  </TFuelModuleDescriptor>
  <TFuelModuleDescriptor id="23739">
    <ControllerName>FuelController</ControllerName>
    <FuelCapacity>500</FuelCapacity>
    <FuelMoveDuration>250</FuelMoveDuration>
  </TFuelModuleDescriptor>
  <TFuelModuleDescriptor id="23752">
    <ControllerName>FuelController</ControllerName>
    <FuelCapacity>500</FuelCapacity>
    <FuelMoveDuration>500</FuelMoveDuration>
  </TFuelModuleDescriptor>
  <TFuelModuleDescriptor id="23767">
    <ControllerName>FuelController</ControllerName>
    <FuelCapacity>350</FuelCapacity>
    <FuelMoveDuration>600</FuelMoveDuration>
  </TFuelModuleDescriptor>
  <TFuelModuleDescriptor id="23783">
    <ControllerName>FuelController</ControllerName>
    <FuelCapacity>550</FuelCapacity>
    <FuelMoveDuration>500</FuelMoveDuration>
  </TFuelModuleDescriptor>
  <TFuelModuleDescriptor id="23796">
    <ControllerName>FuelController</ControllerName>
    <FuelCapacity>800</FuelCapacity>
    <FuelMoveDuration>500</FuelMoveDuration>
  </TFuelModuleDescriptor>
  <TFuelModuleDescriptor id="23815">
    <ControllerName>FuelController</ControllerName>
    <FuelCapacity>2000</FuelCapacity>
    <FuelMoveDuration>500</FuelMoveDuration>
  </TFuelModuleDescriptor>
  <TFuelModuleDescriptor id="23902">
    <ControllerName>FuelController</ControllerName>
    <FuelCapacity>450</FuelCapacity>
    <FuelMoveDuration>500</FuelMoveDuration>
  </TFuelModuleDescriptor>
  <TFuelModuleDescriptor id="23929">
    <ControllerName>FuelController</ControllerName>
    <FuelCapacity>150</FuelCapacity>
    <FuelMoveDuration>600</FuelMoveDuration>
  </TFuelModuleDescriptor>
  <TFuelModuleDescriptor id="23938">
    <ControllerName>FuelController</ControllerName>
    <FuelCapacity>360</FuelCapacity>
    <FuelMoveDuration>480</FuelMoveDuration>
  </TFuelModuleDescriptor>
  <TFuelModuleDescriptor id="23949">
    <ControllerName>FuelController</ControllerName>
    <FuelCapacity>1000</FuelCapacity>
    <FuelMoveDuration>500</FuelMoveDuration>
  </TFuelModuleDescriptor>
  <TFuelModuleDescriptor id="23957">
    <ControllerName>FuelController</ControllerName>
    <FuelCapacity>500</FuelCapacity>
    <FuelMoveDuration>600</FuelMoveDuration>
  </TFuelModuleDescriptor>
  <TFuelModuleDescriptor id="23978">
    <ControllerName>FuelController</ControllerName>
    <FuelCapacity>500</FuelCapacity>
    <FuelMoveDuration>1000</FuelMoveDuration>
  </TFuelModuleDescriptor>
  <TFuelModuleDescriptor id="23990">
    <ControllerName>FuelController</ControllerName>
    <FuelCapacity>500</FuelCapacity>
    <FuelMoveDuration>900</FuelMoveDuration>
  </TFuelModuleDescriptor>
  <TFuelModuleDescriptor id="24002">
    <ControllerName>FuelController</ControllerName>
    <FuelCapacity>480</FuelCapacity>
    <FuelMoveDuration>400</FuelMoveDuration>
  </TFuelModuleDescriptor>
  <TFuelModuleDescriptor id="24008">
    <ControllerName>FuelController</ControllerName>
    <FuelCapacity>450</FuelCapacity>
    <FuelMoveDuration>300</FuelMoveDuration>
  </TFuelModuleDescriptor>
  <TFuelModuleDescriptor id="24021">
    <ControllerName>FuelController</ControllerName>
    <FuelCapacity>1000</FuelCapacity>
    <FuelMoveDuration>600</FuelMoveDuration>
  </TFuelModuleDescriptor>
  <TFuelModuleDescriptor id="24060">
    <ControllerName>FuelController</ControllerName>
    <FuelCapacity>1000</FuelCapacity>
    <FuelMoveDuration>530</FuelMoveDuration>
  </TFuelModuleDescriptor>
  <TFuelModuleDescriptor id="24068">
    <ControllerName>FuelController</ControllerName>
    <FuelCapacity>1300</FuelCapacity>
    <FuelMoveDuration>550</FuelMoveDuration>
  </TFuelModuleDescriptor>
  <TFuelModuleDescriptor id="24160">
    <ControllerName>FuelController</ControllerName>
    <FuelCapacity>1000</FuelCapacity>
    <FuelMoveDuration>420</FuelMoveDuration>
  </TFuelModuleDescriptor>
  <TFuelModuleDescriptor id="24167">
    <ControllerName>FuelController</ControllerName>
    <FuelCapacity>300</FuelCapacity>
    <FuelMoveDuration>660</FuelMoveDuration>
  </TFuelModuleDescriptor>
  <TFuelModuleDescriptor id="24192">
    <ControllerName>FuelController</ControllerName>
    <FuelCapacity>200</FuelCapacity>
    <FuelMoveDuration>600</FuelMoveDuration>
  </TFuelModuleDescriptor>
  <TFuelModuleDescriptor id="24207">
    <ControllerName>FuelController</ControllerName>
    <FuelCapacity>200</FuelCapacity>
    <FuelMoveDuration>360</FuelMoveDuration>
  </TFuelModuleDescriptor>
  <TFuelModuleDescriptor id="24283">
    <ControllerName>FuelController</ControllerName>
    <FuelCapacity>420</FuelCapacity>
    <FuelMoveDuration>1200</FuelMoveDuration>
  </TFuelModuleDescriptor>
  <TFuelModuleDescriptor id="24304">
    <ControllerName>FuelController</ControllerName>
    <FuelCapacity>460</FuelCapacity>
    <FuelMoveDuration>600</FuelMoveDuration>
  </TFuelModuleDescriptor>
  <TFuelModuleDescriptor id="24310">
    <ControllerName>FuelController</ControllerName>
    <FuelCapacity>80</FuelCapacity>
    <FuelMoveDuration>750</FuelMoveDuration>
  </TFuelModuleDescriptor>
  <TFuelModuleDescriptor id="24342">
    <ControllerName>FuelController</ControllerName>
    <FuelCapacity>1000</FuelCapacity>
    <FuelMoveDuration>850</FuelMoveDuration>
  </TFuelModuleDescriptor>
  <TFuelModuleDescriptor id="24349">
    <ControllerName>FuelController</ControllerName>
    <FuelCapacity>600</FuelCapacity>
    <FuelMoveDuration>320</FuelMoveDuration>
  </TFuelModuleDescriptor>
  <TFuelModuleDescriptor id="24367">
    <ControllerName>FuelController</ControllerName>
    <FuelCapacity>600</FuelCapacity>
    <FuelMoveDuration>300</FuelMoveDuration>
  </TFuelModuleDescriptor>
  <TFuelModuleDescriptor id="24373">
    <ControllerName>FuelController</ControllerName>
    <FuelCapacity>600</FuelCapacity>
    <FuelMoveDuration>450</FuelMoveDuration>
  </TFuelModuleDescriptor>
  <TFuelModuleDescriptor id="24386">
    <ControllerName>FuelController</ControllerName>
    <FuelCapacity>450</FuelCapacity>
    <FuelMoveDuration>600</FuelMoveDuration>
  </TFuelModuleDescriptor>
  <TFuelModuleDescriptor id="24458">
    <ControllerName>FuelController</ControllerName>
    <FuelCapacity>1300</FuelCapacity>
    <FuelMoveDuration>500</FuelMoveDuration>
  </TFuelModuleDescriptor>
  <TFuelModuleDescriptor id="24491">
    <ControllerName>FuelController</ControllerName>
    <FuelCapacity>150</FuelCapacity>
    <FuelMoveDuration>500</FuelMoveDuration>
  </TFuelModuleDescriptor>
  <TFuelModuleDescriptor id="24504">
    <ControllerName>FuelController</ControllerName>
    <FuelCapacity>300</FuelCapacity>
    <FuelMoveDuration>750</FuelMoveDuration>
  </TFuelModuleDescriptor>
  <TFuelModuleDescriptor id="24546">
    <ControllerName>FuelController</ControllerName>
    <FuelCapacity>300</FuelCapacity>
    <FuelMoveDuration>600</FuelMoveDuration>
  </TFuelModuleDescriptor>
  <TFuelModuleDescriptor id="24568">
    <ControllerName>FuelController</ControllerName>
    <FuelCapacity>290</FuelCapacity>
    <FuelMoveDuration>750</FuelMoveDuration>
  </TFuelModuleDescriptor>
  <TFuelModuleDescriptor id="24596">
    <ControllerName>FuelController</ControllerName>
    <FuelCapacity>120</FuelCapacity>
    <FuelMoveDuration>285</FuelMoveDuration>
  </TFuelModuleDescriptor>
  <TFuelModuleDescriptor id="24614">
    <ControllerName>FuelController</ControllerName>
    <FuelCapacity>300</FuelCapacity>
    <FuelMoveDuration>500</FuelMoveDuration>
  </TFuelModuleDescriptor>
  <TFuelModuleDescriptor id="24625">
    <ControllerName>FuelController</ControllerName>
    <FuelCapacity>350</FuelCapacity>
    <FuelMoveDuration>500</FuelMoveDuration>
  </TFuelModuleDescriptor>
  <TFuelModuleDescriptor id="24659">
    <ControllerName>FuelController</ControllerName>
    <FuelCapacity>400</FuelCapacity>
    <FuelMoveDuration>800</FuelMoveDuration>
  </TFuelModuleDescriptor>
  <TFuelModuleDescriptor id="24673">
    <ControllerName>FuelController</ControllerName>
    <FuelCapacity>100</FuelCapacity>
    <FuelMoveDuration>500</FuelMoveDuration>
  </TFuelModuleDescriptor>
  <TFuelModuleDescriptor id="24685">
    <ControllerName>FuelController</ControllerName>
    <FuelCapacity>300</FuelCapacity>
    <FuelMoveDuration>550</FuelMoveDuration>
  </TFuelModuleDescriptor>
  <TFuelModuleDescriptor id="24697">
    <ControllerName>FuelController</ControllerName>
    <FuelCapacity>400</FuelCapacity>
    <FuelMoveDuration>350</FuelMoveDuration>
  </TFuelModuleDescriptor>
  <TFuelModuleDescriptor id="24714">
    <ControllerName>FuelController</ControllerName>
    <FuelCapacity>400</FuelCapacity>
    <FuelMoveDuration>500</FuelMoveDuration>
  </TFuelModuleDescriptor>
  <TFuelModuleDescriptor id="24766">
    <ControllerName>FuelController</ControllerName>
    <FuelCapacity>80</FuelCapacity>
    <FuelMoveDuration>500</FuelMoveDuration>
  </TFuelModuleDescriptor>
  <TFuelModuleDescriptor id="24773">
    <ControllerName>FuelController</ControllerName>
    <FuelCapacity>1500</FuelCapacity>
    <FuelMoveDuration>230</FuelMoveDuration>
  </TFuelModuleDescriptor>
  <TFuelModuleDescriptor id="24787">
    <ControllerName>FuelController</ControllerName>
    <FuelCapacity>750</FuelCapacity>
    <FuelMoveDuration>480</FuelMoveDuration>
  </TFuelModuleDescriptor>
  <TFuelModuleDescriptor id="24799">
    <ControllerName>FuelController</ControllerName>
    <FuelCapacity>100</FuelCapacity>
    <FuelMoveDuration>600</FuelMoveDuration>
  </TFuelModuleDescriptor>
  <TFuelModuleDescriptor id="24816">
    <ControllerName>FuelController</ControllerName>
    <FuelCapacity>80</FuelCapacity>
    <FuelMoveDuration>400</FuelMoveDuration>
  </TFuelModuleDescriptor>
  <TFuelModuleDescriptor id="24860">
    <ControllerName>FuelController</ControllerName>
    <FuelCapacity>85</FuelCapacity>
    <FuelMoveDuration>700</FuelMoveDuration>
  </TFuelModuleDescriptor>
  <TFuelModuleDescriptor id="24871">
    <ControllerName>FuelController</ControllerName>
    <FuelCapacity>450</FuelCapacity>
    <FuelMoveDuration>1000</FuelMoveDuration>
  </TFuelModuleDescriptor>
  <TFuelModuleDescriptor id="24887">
    <ControllerName>FuelController</ControllerName>
    <FuelCapacity>1000</FuelCapacity>
    <FuelMoveDuration>650</FuelMoveDuration>
  </TFuelModuleDescriptor>
  <TFuelModuleDescriptor id="24895">
    <ControllerName>FuelController</ControllerName>
    <FuelCapacity>400</FuelCapacity>
    <FuelMoveDuration>450</FuelMoveDuration>
  </TFuelModuleDescriptor>
  <TFuelModuleDescriptor id="24950">
    <ControllerName>FuelController</ControllerName>
    <FuelCapacity>600</FuelCapacity>
    <FuelMoveDuration>500</FuelMoveDuration>
  </TFuelModuleDescriptor>
  <TFuelModuleDescriptor id="25021">
    <ControllerName>FuelController</ControllerName>
    <FuelCapacity>950</FuelCapacity>
    <FuelMoveDuration>450</FuelMoveDuration>
  </TFuelModuleDescriptor>
  <TFuelModuleDescriptor id="25029">
    <ControllerName>FuelController</ControllerName>
    <FuelCapacity>1200</FuelCapacity>
    <FuelMoveDuration>600</FuelMoveDuration>
  </TFuelModuleDescriptor>
  <TFuelModuleDescriptor id="25048">
    <ControllerName>FuelController</ControllerName>
    <FuelCapacity>60</FuelCapacity>
    <FuelMoveDuration>1000</FuelMoveDuration>
  </TFuelModuleDescriptor>
  <TFuelModuleDescriptor id="25061">
    <ControllerName>FuelController</ControllerName>
    <FuelCapacity>1200</FuelCapacity>
    <FuelMoveDuration>500</FuelMoveDuration>
  </TFuelModuleDescriptor>
  <TFuelModuleDescriptor id="25069">
    <ControllerName>FuelController</ControllerName>
    <FuelCapacity>1500</FuelCapacity>
    <FuelMoveDuration>480</FuelMoveDuration>
  </TFuelModuleDescriptor>
  <TFuelModuleDescriptor id="25081">
    <ControllerName>FuelController</ControllerName>
    <FuelCapacity>1500</FuelCapacity>
    <FuelMoveDuration>500</FuelMoveDuration>
  </TFuelModuleDescriptor>
  <TFuelModuleDescriptor id="25089">
    <ControllerName>FuelController</ControllerName>
    <FuelCapacity>955</FuelCapacity>
    <FuelMoveDuration>400</FuelMoveDuration>
  </TFuelModuleDescriptor>
  <TFuelModuleDescriptor id="25096">
    <ControllerName>FuelController</ControllerName>
    <FuelCapacity>1360</FuelCapacity>
    <FuelMoveDuration>700</FuelMoveDuration>
  </TFuelModuleDescriptor>
  <TFuelModuleDescriptor id="25121">
    <ControllerName>FuelController</ControllerName>
    <FuelCapacity>1100</FuelCapacity>
    <FuelMoveDuration>450</FuelMoveDuration>
  </TFuelModuleDescriptor>
  <TFuelModuleDescriptor id="25127">
    <ControllerName>FuelController</ControllerName>
    <FuelCapacity>300</FuelCapacity>
    <FuelMoveDuration>450</FuelMoveDuration>
  </TFuelModuleDescriptor>
  <TFuelModuleDescriptor id="25138">
    <ControllerName>FuelController</ControllerName>
    <FuelCapacity>200</FuelCapacity>
    <FuelMoveDuration>500</FuelMoveDuration>
  </TFuelModuleDescriptor>
  <TFuelModuleDescriptor id="25217">
    <ControllerName>FuelController</ControllerName>
    <FuelCapacity>1950</FuelCapacity>
    <FuelMoveDuration>550</FuelMoveDuration>
  </TFuelModuleDescriptor>
  <TFuelModuleDescriptor id="25343">
    <ControllerName>FuelController</ControllerName>
    <FuelCapacity>250</FuelCapacity>
    <FuelMoveDuration>700</FuelMoveDuration>
  </TFuelModuleDescriptor>
  <TFuelModuleDescriptor id="25354">
    <ControllerName>FuelController</ControllerName>
    <FuelCapacity>450</FuelCapacity>
    <FuelMoveDuration>450</FuelMoveDuration>
  </TFuelModuleDescriptor>
  <TFuelModuleDescriptor id="25380">
    <ControllerName>FuelController</ControllerName>
    <FuelCapacity>500</FuelCapacity>
    <FuelMoveDuration>650</FuelMoveDuration>
  </TFuelModuleDescriptor>
  <TFuelModuleDescriptor id="25397">
    <ControllerName>FuelController</ControllerName>
    <FuelCapacity>350</FuelCapacity>
    <FuelMoveDuration>650</FuelMoveDuration>
  </TFuelModuleDescriptor>
  <TFuelModuleDescriptor id="25410">
    <ControllerName>FuelController</ControllerName>
    <FuelCapacity>350</FuelCapacity>
    <FuelMoveDuration>350</FuelMoveDuration>
  </TFuelModuleDescriptor>
  <TFuelModuleDescriptor id="25421">
    <ControllerName>FuelController</ControllerName>
    <FuelCapacity>450</FuelCapacity>
    <FuelMoveDuration>480</FuelMoveDuration>
  </TFuelModuleDescriptor>
  <TFuelModuleDescriptor id="25432">
    <ControllerName>FuelController</ControllerName>
    <FuelCapacity>450</FuelCapacity>
    <FuelMoveDuration>390</FuelMoveDuration>
  </TFuelModuleDescriptor>
  <TFuelModuleDescriptor id="25439">
    <ControllerName>FuelController</ControllerName>
    <FuelCapacity>400</FuelCapacity>
    <FuelMoveDuration>650</FuelMoveDuration>
  </TFuelModuleDescriptor>
  <TFuelModuleDescriptor id="25446">
    <ControllerName>FuelController</ControllerName>
    <FuelCapacity>250</FuelCapacity>
    <FuelMoveDuration>480</FuelMoveDuration>
  </TFuelModuleDescriptor>
  <TFuelModuleDescriptor id="25453">
    <ControllerName>FuelController</ControllerName>
    <FuelCapacity>450</FuelCapacity>
    <FuelMoveDuration>650</FuelMoveDuration>
  </TFuelModuleDescriptor>
  <TFuelModuleDescriptor id="25460">
    <ControllerName>FuelController</ControllerName>
    <FuelCapacity>750</FuelCapacity>
    <FuelMoveDuration>650</FuelMoveDuration>
  </TFuelModuleDescriptor>
  <TFuelModuleDescriptor id="25494">
    <ControllerName>FuelController</ControllerName>
    <FuelCapacity>100</FuelCapacity>
    <FuelMoveDuration>300</FuelMoveDuration>
  </TFuelModuleDescriptor>
  <TFuelModuleDescriptor id="25507">
    <ControllerName>FuelController</ControllerName>
    <FuelCapacity>150</FuelCapacity>
    <FuelMoveDuration>450</FuelMoveDuration>
  </TFuelModuleDescriptor>
  <TFuelModuleDescriptor id="25538">
    <ControllerName>FuelController</ControllerName>
    <FuelCapacity>330</FuelCapacity>
    <FuelMoveDuration>710</FuelMoveDuration>
  </TFuelModuleDescriptor>
  <TFuelModuleDescriptor id="25596">
    <ControllerName>FuelController</ControllerName>
    <FuelCapacity>800</FuelCapacity>
    <FuelMoveDuration>350</FuelMoveDuration>
  </TFuelModuleDescriptor>
  <TFuelModuleDescriptor id="25603">
    <ControllerName>FuelController</ControllerName>
    <FuelCapacity>500</FuelCapacity>
    <FuelMoveDuration>350</FuelMoveDuration>
  </TFuelModuleDescriptor>
  <TFuelModuleDescriptor id="25644">
    <ControllerName>FuelController</ControllerName>
    <FuelCapacity>500</FuelCapacity>
    <FuelMoveDuration>800</FuelMoveDuration>
  </TFuelModuleDescriptor>
  <TFuelModuleDescriptor id="25710">
    <ControllerName>FuelController</ControllerName>
    <FuelCapacity>420</FuelCapacity>
    <FuelMoveDuration>410</FuelMoveDuration>
  </TFuelModuleDescriptor>
  <TFuelModuleDescriptor id="25773">
    <ControllerName>FuelController</ControllerName>
    <FuelCapacity>500</FuelCapacity>
    <FuelMoveDuration>320</FuelMoveDuration>
  </TFuelModuleDescriptor>
  <TFuelModuleDescriptor id="25781">
    <ControllerName>FuelController</ControllerName>
    <FuelCapacity>300</FuelCapacity>
    <FuelMoveDuration>250</FuelMoveDuration>
  </TFuelModuleDescriptor>
  <TFuelModuleDescriptor id="25789">
    <ControllerName>FuelController</ControllerName>
    <FuelCapacity>400</FuelCapacity>
    <FuelMoveDuration>550</FuelMoveDuration>
  </TFuelModuleDescriptor>
  <TFuelModuleDescriptor id="25825">
    <ControllerName>FuelController</ControllerName>
    <FuelCapacity>65</FuelCapacity>
    <FuelMoveDuration>1000</FuelMoveDuration>
  </TFuelModuleDescriptor>
  <TFuelModuleDescriptor id="25923">
    <ControllerName>FuelController</ControllerName>
    <FuelCapacity>75</FuelCapacity>
    <FuelMoveDuration>500</FuelMoveDuration>
  </TFuelModuleDescriptor>
  <TFuelModuleDescriptor id="25963">
    <ControllerName>FuelController</ControllerName>
    <FuelCapacity>350</FuelCapacity>
    <FuelMoveDuration>480</FuelMoveDuration>
  </TFuelModuleDescriptor>
  <TFuelModuleDescriptor id="25990">
    <ControllerName>FuelController</ControllerName>
    <FuelCapacity>1100</FuelCapacity>
    <FuelMoveDuration>720</FuelMoveDuration>
  </TFuelModuleDescriptor>
  <TFuelModuleDescriptor id="25996">
    <ControllerName>FuelController</ControllerName>
    <FuelCapacity>1000</FuelCapacity>
    <FuelMoveDuration>350</FuelMoveDuration>
  </TFuelModuleDescriptor>
  <TFuelModuleDescriptor id="26002">
    <ControllerName>FuelController</ControllerName>
    <FuelCapacity>1000</FuelCapacity>
    <FuelMoveDuration>700</FuelMoveDuration>
  </TFuelModuleDescriptor>
  <TFuelModuleDescriptor id="26046">
    <ControllerName>FuelController</ControllerName>
    <FuelCapacity>300</FuelCapacity>
    <FuelMoveDuration>300</FuelMoveDuration>
  </TFuelModuleDescriptor>
  <TFuelModuleDescriptor id="26057">
    <ControllerName>FuelController</ControllerName>
    <FuelCapacity>220</FuelCapacity>
    <FuelMoveDuration>800</FuelMoveDuration>
  </TFuelModuleDescriptor>
  <TFuelModuleDescriptor id="26064">
    <ControllerName>FuelController</ControllerName>
    <FuelCapacity>500</FuelCapacity>
    <FuelMoveDuration>850</FuelMoveDuration>
  </TFuelModuleDescriptor>
  <TFuelModuleDescriptor id="26097">
    <ControllerName>FuelController</ControllerName>
    <FuelCapacity>750</FuelCapacity>
    <FuelMoveDuration>250</FuelMoveDuration>
  </TFuelModuleDescriptor>
  <TFuelModuleDescriptor id="26113">
    <ControllerName>FuelController</ControllerName>
    <FuelCapacity>650</FuelCapacity>
    <FuelMoveDuration>400</FuelMoveDuration>
  </TFuelModuleDescriptor>
  <TFuelModuleDescriptor id="26121">
    <ControllerName>FuelController</ControllerName>
    <FuelCapacity>1000</FuelCapacity>
    <FuelMoveDuration>300</FuelMoveDuration>
  </TFuelModuleDescriptor>
  <TFuelModuleDescriptor id="26264">
    <ControllerName>FuelController</ControllerName>
    <FuelCapacity>600</FuelCapacity>
    <FuelMoveDuration>1000</FuelMoveDuration>
  </TFuelModuleDescriptor>
  <TFuelModuleDescriptor id="26282">
    <ControllerName>FuelController</ControllerName>
    <FuelCapacity>100</FuelCapacity>
    <FuelMoveDuration>400</FuelMoveDuration>
  </TFuelModuleDescriptor>
  <TFuelModuleDescriptor id="26289">
    <ControllerName>FuelController</ControllerName>
    <FuelCapacity>250</FuelCapacity>
    <FuelMoveDuration>1600</FuelMoveDuration>
  </TFuelModuleDescriptor>
  <TFuelModuleDescriptor id="26295">
    <ControllerName>FuelController</ControllerName>
    <FuelCapacity>150</FuelCapacity>
    <FuelMoveDuration>1000</FuelMoveDuration>
  </TFuelModuleDescriptor>
  <TFuelModuleDescriptor id="26301">
    <ControllerName>FuelController</ControllerName>
    <FuelCapacity>700</FuelCapacity>
    <FuelMoveDuration>480</FuelMoveDuration>
  </TFuelModuleDescriptor>
  <TFuelModuleDescriptor id="26308">
    <ControllerName>FuelController</ControllerName>
    <FuelCapacity>680</FuelCapacity>
    <FuelMoveDuration>480</FuelMoveDuration>
  </TFuelModuleDescriptor>
  <TFuelModuleDescriptor id="26320">
    <ControllerName>FuelController</ControllerName>
    <FuelCapacity>300</FuelCapacity>
    <FuelMoveDuration>240</FuelMoveDuration>
  </TFuelModuleDescriptor>
  <TFuelModuleDescriptor id="26335">
    <ControllerName>FuelController</ControllerName>
    <FuelCapacity>1700</FuelCapacity>
    <FuelMoveDuration>650</FuelMoveDuration>
  </TFuelModuleDescriptor>
  <TFuelModuleDescriptor id="26450">
    <ControllerName>FuelController</ControllerName>
    <FuelCapacity>250</FuelCapacity>
    <FuelMoveDuration>150</FuelMoveDuration>
  </TFuelModuleDescriptor>
  <TFuelModuleDescriptor id="26488">
    <ControllerName>FuelController</ControllerName>
    <FuelCapacity>510</FuelCapacity>
    <FuelMoveDuration>350</FuelMoveDuration>
  </TFuelModuleDescriptor>
  <TFuelModuleDescriptor id="26660">
    <ControllerName>FuelController</ControllerName>
    <FuelCapacity>420</FuelCapacity>
    <FuelMoveDuration>450</FuelMoveDuration>
  </TFuelModuleDescriptor>
  <TFuelModuleDescriptor id="26751">
    <ControllerName>FuelController</ControllerName>
    <FuelCapacity>450</FuelCapacity>
    <FuelMoveDuration>200</FuelMoveDuration>
  </TFuelModuleDescriptor>
  <TFuelModuleDescriptor id="26774">
    <ControllerName>FuelController</ControllerName>
    <FuelCapacity>2000</FuelCapacity>
    <FuelMoveDuration>450</FuelMoveDuration>
  </TFuelModuleDescriptor>
  <TFuelModuleDescriptor id="26863">
    <ControllerName>FuelController</ControllerName>
    <FuelCapacity>700</FuelCapacity>
    <FuelMoveDuration>250</FuelMoveDuration>
  </TFuelModuleDescriptor>
  <TFuelModuleDescriptor id="26901">
    <ControllerName>FuelController</ControllerName>
    <FuelCapacity>400</FuelCapacity>
    <FuelMoveDuration>200</FuelMoveDuration>
  </TFuelModuleDescriptor>
  <TFuelModuleDescriptor id="26912">
    <ControllerName>FuelController</ControllerName>
    <FuelCapacity>950</FuelCapacity>
    <FuelMoveDuration>750</FuelMoveDuration>
  </TFuelModuleDescriptor>
  <TFuelModuleDescriptor id="26923">
    <ControllerName>FuelController</ControllerName>
    <FuelCapacity>1000</FuelCapacity>
    <FuelMoveDuration>250</FuelMoveDuration>
  </TFuelModuleDescriptor>
  <TFuelModuleDescriptor id="26935">
    <ControllerName>FuelController</ControllerName>
    <FuelCapacity>800</FuelCapacity>
    <FuelMoveDuration>200</FuelMoveDuration>
  </TFuelModuleDescriptor>
  <TFuelModuleDescriptor id="26960">
    <ControllerName>FuelController</ControllerName>
    <FuelCapacity>1450</FuelCapacity>
    <FuelMoveDuration>480</FuelMoveDuration>
  </TFuelModuleDescriptor>
  <TFuelModuleDescriptor id="27003">
    <ControllerName>FuelController</ControllerName>
    <FuelCapacity>1000</FuelCapacity>
    <FuelMoveDuration>550</FuelMoveDuration>
  </TFuelModuleDescriptor>
  <TFuelModuleDescriptor id="27019">
    <ControllerName>FuelController</ControllerName>
    <FuelCapacity>100</FuelCapacity>
    <FuelMoveDuration>630</FuelMoveDuration>
  </TFuelModuleDescriptor>
  <TFuelModuleDescriptor id="27033">
    <ControllerName>FuelController</ControllerName>
    <FuelCapacity>450</FuelCapacity>
    <FuelMoveDuration>430</FuelMoveDuration>
  </TFuelModuleDescriptor>
  <TFuelModuleDescriptor id="27099">
    <ControllerName>FuelController</ControllerName>
    <FuelCapacity>200</FuelCapacity>
    <FuelMoveDuration>300</FuelMoveDuration>
  </TFuelModuleDescriptor>
  <TFuelModuleDescriptor id="27146">
    <ControllerName>FuelController</ControllerName>
    <FuelCapacity>650</FuelCapacity>
    <FuelMoveDuration>450</FuelMoveDuration>
  </TFuelModuleDescriptor>
  <TFuelModuleDescriptor id="27152">
    <ControllerName>FuelController</ControllerName>
    <FuelCapacity>210</FuelCapacity>
    <FuelMoveDuration>560</FuelMoveDuration>
  </TFuelModuleDescriptor>
  <TFuelModuleDescriptor id="27221">
    <ControllerName>FuelController</ControllerName>
    <FuelCapacity>500</FuelCapacity>
    <FuelMoveDuration>400</FuelMoveDuration>
  </TFuelModuleDescriptor>
  <TFuelModuleDescriptor id="27273">
    <ControllerName>FuelController</ControllerName>
    <FuelCapacity>650</FuelCapacity>
    <FuelMoveDuration>520</FuelMoveDuration>
  </TFuelModuleDescriptor>
  <TFuelModuleDescriptor id="27403">
    <ControllerName>FuelController</ControllerName>
    <FuelCapacity>80</FuelCapacity>
    <FuelMoveDuration>450</FuelMoveDuration>
  </TFuelModuleDescriptor>
  <TFuelModuleDescriptor id="27431">
    <ControllerName>FuelController</ControllerName>
    <FuelCapacity>450</FuelCapacity>
    <FuelMoveDuration>400</FuelMoveDuration>
  </TFuelModuleDescriptor>
  <TFuelModuleDescriptor id="27534">
    <ControllerName>FuelController</ControllerName>
    <FuelCapacity>75</FuelCapacity>
    <FuelMoveDuration>800</FuelMoveDuration>
  </TFuelModuleDescriptor>
  <TFuelModuleDescriptor id="27584">
    <ControllerName>FuelController</ControllerName>
    <FuelCapacity>250</FuelCapacity>
    <FuelMoveDuration>500</FuelMoveDuration>
  </TFuelModuleDescriptor>
  <TFuelModuleDescriptor id="27605">
    <ControllerName>FuelController</ControllerName>
    <FuelCapacity>1200</FuelCapacity>
    <FuelMoveDuration>450</FuelMoveDuration>
  </TFuelModuleDescriptor>
  <TFuelModuleDescriptor id="27691">
    <ControllerName>FuelController</ControllerName>
    <FuelCapacity>330</FuelCapacity>
    <FuelMoveDuration>270</FuelMoveDuration>
  </TFuelModuleDescriptor>
  <TFuelModuleDescriptor id="27711">
    <ControllerName>FuelController</ControllerName>
    <FuelCapacity>200</FuelCapacity>
    <FuelMoveDuration>700</FuelMoveDuration>
  </TFuelModuleDescriptor>
  <TFuelModuleDescriptor id="27737">
    <ControllerName>FuelController</ControllerName>
    <FuelCapacity>50</FuelCapacity>
    <FuelMoveDuration>350</FuelMoveDuration>
  </TFuelModuleDescriptor>
  <TFuelModuleDescriptor id="27870">
    <ControllerName>FuelController</ControllerName>
    <FuelCapacity>200</FuelCapacity>
    <FuelMoveDuration>450</FuelMoveDuration>
  </TFuelModuleDescriptor>
  <TFuelModuleDescriptor id="28132">
    <ControllerName>FuelController</ControllerName>
    <FuelCapacity>700</FuelCapacity>
    <FuelMoveDuration>400</FuelMoveDuration>
  </TFuelModuleDescriptor>
  <TFuelModuleDescriptor id="28152">
    <ControllerName>FuelController</ControllerName>
    <FuelCapacity>100</FuelCapacity>
    <FuelMoveDuration>650</FuelMoveDuration>
  </TFuelModuleDescriptor>
  <TFuelModuleDescriptor id="28188">
    <ControllerName>FuelController</ControllerName>
    <FuelCapacity>200</FuelCapacity>
    <FuelMoveDuration>660</FuelMoveDuration>
  </TFuelModuleDescriptor>
  <TFuelModuleDescriptor id="28293">
    <ControllerName>FuelController</ControllerName>
    <FuelCapacity>85</FuelCapacity>
    <FuelMoveDuration>400</FuelMoveDuration>
  </TFuelModuleDescriptor>
  <TFuelModuleDescriptor id="28304">
    <ControllerName>FuelController</ControllerName>
    <FuelCapacity>300</FuelCapacity>
    <FuelMoveDuration>1000</FuelMoveDuration>
  </TFuelModuleDescriptor>
  <TFuelModuleDescriptor id="28316">
    <ControllerName>FuelController</ControllerName>
    <FuelCapacity>400</FuelCapacity>
    <FuelMoveDuration>600</FuelMoveDuration>
  </TFuelModuleDescriptor>
  <TFuelModuleDescriptor id="28340">
    <ControllerName>FuelController</ControllerName>
    <FuelCapacity>1350</FuelCapacity>
    <FuelMoveDuration>560</FuelMoveDuration>
  </TFuelModuleDescriptor>
  <TFuelModuleDescriptor id="28346">
    <ControllerName>FuelController</ControllerName>
    <FuelCapacity>250</FuelCapacity>
    <FuelMoveDuration>300</FuelMoveDuration>
  </TFuelModuleDescriptor>
  <TFuelModuleDescriptor id="28352">
    <ControllerName>FuelController</ControllerName>
    <FuelCapacity>120</FuelCapacity>
    <FuelMoveDuration>200</FuelMoveDuration>
  </TFuelModuleDescriptor>
  <TFuelModuleDescriptor id="28359">
    <ControllerName>FuelController</ControllerName>
    <FuelCapacity>600</FuelCapacity>
    <FuelMoveDuration>700</FuelMoveDuration>
  </TFuelModuleDescriptor>
  <TFuelModuleDescriptor id="28402">
    <ControllerName>FuelController</ControllerName>
    <FuelCapacity>250</FuelCapacity>
    <FuelMoveDuration>320</FuelMoveDuration>
  </TFuelModuleDescriptor>
  <TFuelModuleDescriptor id="28408">
    <ControllerName>FuelController</ControllerName>
    <FuelCapacity>1000</FuelCapacity>
    <FuelMoveDuration>450</FuelMoveDuration>
  </TFuelModuleDescriptor>
  <TFuelModuleDescriptor id="28496">
    <ControllerName>FuelController</ControllerName>
    <FuelCapacity>1360</FuelCapacity>
    <FuelMoveDuration>650</FuelMoveDuration>
  </TFuelModuleDescriptor>
  <TFuelModuleDescriptor id="28517">
    <ControllerName>FuelController</ControllerName>
    <FuelCapacity>1250</FuelCapacity>
    <FuelMoveDuration>500</FuelMoveDuration>
  </TFuelModuleDescriptor>
  <TFuelModuleDescriptor id="28530">
    <ControllerName>FuelController</ControllerName>
    <FuelCapacity>1250</FuelCapacity>
    <FuelMoveDuration>600</FuelMoveDuration>
  </TFuelModuleDescriptor>
  <TFuelModuleDescriptor id="28565">
    <ControllerName>FuelController</ControllerName>
    <FuelCapacity>1250</FuelCapacity>
    <FuelMoveDuration>900</FuelMoveDuration>
  </TFuelModuleDescriptor>
  <TFuelModuleDescriptor id="28644">
    <ControllerName>FuelController</ControllerName>
    <FuelCapacity>2000</FuelCapacity>
    <FuelMoveDuration>600</FuelMoveDuration>
  </TFuelModuleDescriptor>
  <TFuelModuleDescriptor id="28660">
    <ControllerName>FuelController</ControllerName>
    <FuelCapacity>2000</FuelCapacity>
    <FuelMoveDuration>550</FuelMoveDuration>
  </TFuelModuleDescriptor>
  <TFuelModuleDescriptor id="28729">
    <ControllerName>FuelController</ControllerName>
    <FuelCapacity>115</FuelCapacity>
    <FuelMoveDuration>400</FuelMoveDuration>
  </TFuelModuleDescriptor>
  <TFuelModuleDescriptor id="28819">
    <ControllerName>FuelController</ControllerName>
    <FuelCapacity>1360</FuelCapacity>
    <FuelMoveDuration>550</FuelMoveDuration>
  </TFuelModuleDescriptor>
  <TFuelModuleDescriptor id="28846">
    <ControllerName>FuelController</ControllerName>
    <FuelCapacity>140</FuelCapacity>
    <FuelMoveDuration>250</FuelMoveDuration>
  </TFuelModuleDescriptor>
  <TFuelModuleDescriptor id="28878">
    <ControllerName>FuelController</ControllerName>
    <FuelCapacity>400</FuelCapacity>
    <FuelMoveDuration>300</FuelMoveDuration>
  </TFuelModuleDescriptor>
  <TFuelModuleDescriptor id="28884">
    <ControllerName>FuelController</ControllerName>
    <FuelCapacity>545</FuelCapacity>
    <FuelMoveDuration>500</FuelMoveDuration>
  </TFuelModuleDescriptor>
  <TFuelModuleDescriptor id="28891">
    <ControllerName>FuelController</ControllerName>
    <FuelCapacity>370</FuelCapacity>
    <FuelMoveDuration>545</FuelMoveDuration>
  </TFuelModuleDescriptor>
  <TFuelModuleDescriptor id="28918">
    <ControllerName>FuelController</ControllerName>
    <FuelCapacity>900</FuelCapacity>
    <FuelMoveDuration>400</FuelMoveDuration>
  </TFuelModuleDescriptor>
  <TFuelModuleDescriptor id="28945">
    <ControllerName>FuelController</ControllerName>
    <FuelCapacity>410</FuelCapacity>
    <FuelMoveDuration>300</FuelMoveDuration>
  </TFuelModuleDescriptor>
  <TFuelModuleDescriptor id="28961">
    <ControllerName>FuelController</ControllerName>
    <FuelCapacity>650</FuelCapacity>
    <FuelMoveDuration>300</FuelMoveDuration>
  </TFuelModuleDescriptor>
  <TFuelModuleDescriptor id="28994">
    <ControllerName>FuelController</ControllerName>
    <FuelCapacity>800</FuelCapacity>
    <FuelMoveDuration>400</FuelMoveDuration>
  </TFuelModuleDescriptor>
  <TFuelModuleDescriptor id="29020">
    <ControllerName>FuelController</ControllerName>
    <FuelCapacity>800</FuelCapacity>
    <FuelMoveDuration>450</FuelMoveDuration>
  </TFuelModuleDescriptor>
  <TFuelModuleDescriptor id="29055">
    <ControllerName>FuelController</ControllerName>
    <FuelCapacity>360</FuelCapacity>
    <FuelMoveDuration>450</FuelMoveDuration>
  </TFuelModuleDescriptor>
  <TFuelModuleDescriptor id="29085">
    <ControllerName>FuelController</ControllerName>
    <FuelCapacity>1100</FuelCapacity>
    <FuelMoveDuration>350</FuelMoveDuration>
  </TFuelModuleDescriptor>
  <TFuelModuleDescriptor id="29294">
    <ControllerName>FuelController</ControllerName>
    <FuelCapacity>300</FuelCapacity>
    <FuelMoveDuration>1200</FuelMoveDuration>
  </TFuelModuleDescriptor>
  <TFuelModuleDescriptor id="29325">
    <ControllerName>FuelController</ControllerName>
    <FuelCapacity>120</FuelCapacity>
    <FuelMoveDuration>600</FuelMoveDuration>
  </TFuelModuleDescriptor>
  <TFuelModuleDescriptor id="29406">
    <ControllerName>FuelController</ControllerName>
    <FuelCapacity>45</FuelCapacity>
    <FuelMoveDuration>500</FuelMoveDuration>
  </TFuelModuleDescriptor>
  <TFuelModuleDescriptor id="29427">
    <ControllerName>FuelController</ControllerName>
    <FuelCapacity>300</FuelCapacity>
    <FuelMoveDuration>800</FuelMoveDuration>
  </TFuelModuleDescriptor>
  <TFuelModuleDescriptor id="29442">
    <ControllerName>FuelController</ControllerName>
    <FuelCapacity>350</FuelCapacity>
    <FuelMoveDuration>200</FuelMoveDuration>
  </TFuelModuleDescriptor>
  <TFuelModuleDescriptor id="29657">
    <ControllerName>FuelController</ControllerName>
    <FuelCapacity>150</FuelCapacity>
    <FuelMoveDuration>300</FuelMoveDuration>
  </TFuelModuleDescriptor>
  <TFuelModuleDescriptor id="30091">
    <ControllerName>FuelController</ControllerName>
    <FuelCapacity>1000</FuelCapacity>
    <FuelMoveDuration>575</FuelMoveDuration>
  </TFuelModuleDescriptor>
  <TFuelModuleDescriptor id="30107">
    <ControllerName>FuelController</ControllerName>
    <FuelCapacity>1500</FuelCapacity>
    <FuelMoveDuration>575</FuelMoveDuration>
  </TFuelModuleDescriptor>
  <TFuelModuleDescriptor id="30140">
    <ControllerName>FuelController</ControllerName>
    <FuelCapacity>1500</FuelCapacity>
    <FuelMoveDuration>600</FuelMoveDuration>
  </TFuelModuleDescriptor>
  <TFuelModuleDescriptor id="30158">
    <ControllerName>FuelController</ControllerName>
    <FuelCapacity>1000</FuelCapacity>
    <FuelMoveDuration>470</FuelMoveDuration>
  </TFuelModuleDescriptor>
  <TFuelModuleDescriptor id="30170">
    <ControllerName>FuelController</ControllerName>
    <FuelCapacity>250</FuelCapacity>
    <FuelMoveDuration>680</FuelMoveDuration>
  </TFuelModuleDescriptor>
  <TFuelModuleDescriptor id="30190">
    <ControllerName>FuelController</ControllerName>
    <FuelCapacity>300</FuelCapacity>
    <FuelMoveDuration>680</FuelMoveDuration>
  </TFuelModuleDescriptor>
  <TFuelModuleDescriptor id="30200">
    <ControllerName>FuelController</ControllerName>
    <FuelCapacity>1200</FuelCapacity>
    <FuelMoveDuration>900</FuelMoveDuration>
  </TFuelModuleDescriptor>
  <TFuelModuleDescriptor id="30216">
    <ControllerName>FuelController</ControllerName>
    <FuelCapacity>570</FuelCapacity>
    <FuelMoveDuration>680</FuelMoveDuration>
  </TFuelModuleDescriptor>
  <TFuelModuleDescriptor id="30224">
    <ControllerName>FuelController</ControllerName>
    <FuelCapacity>800</FuelCapacity>
    <FuelMoveDuration>300</FuelMoveDuration>
  </TFuelModuleDescriptor>
  <TFuelModuleDescriptor id="30231">
    <ControllerName>FuelController</ControllerName>
    <FuelCapacity>250</FuelCapacity>
    <FuelMoveDuration>550</FuelMoveDuration>
  </TFuelModuleDescriptor>
  <TFuelModuleDescriptor id="30237">
    <ControllerName>FuelController</ControllerName>
    <FuelCapacity>570</FuelCapacity>
    <FuelMoveDuration>575</FuelMoveDuration>
  </TFuelModuleDescriptor>
  <TFuelModuleDescriptor id="30261">
    <ControllerName>FuelController</ControllerName>
    <FuelCapacity>900</FuelCapacity>
    <FuelMoveDuration>500</FuelMoveDuration>
  </TFuelModuleDescriptor>
  <TFuelModuleDescriptor id="30274">
    <ControllerName>FuelController</ControllerName>
    <FuelCapacity>1500</FuelCapacity>
    <FuelMoveDuration>460</FuelMoveDuration>
  </TFuelModuleDescriptor>
  <TFuelModuleDescriptor id="30295">
    <ControllerName>FuelController</ControllerName>
    <FuelCapacity>2000</FuelCapacity>
    <FuelMoveDuration>2000</FuelMoveDuration>
  </TFuelModuleDescriptor>
  <TFuelModuleDescriptor id="30339">
    <ControllerName>FuelController</ControllerName>
    <FuelCapacity>950</FuelCapacity>
    <FuelMoveDuration>685</FuelMoveDuration>
  </TFuelModuleDescriptor>
  <TFuelModuleDescriptor id="30357">
    <ControllerName>FuelController</ControllerName>
    <FuelCapacity>450</FuelCapacity>
    <FuelMoveDuration>680</FuelMoveDuration>
  </TFuelModuleDescriptor>
  <TFuelModuleDescriptor id="30369">
    <ControllerName>FuelController</ControllerName>
    <FuelCapacity>450</FuelCapacity>
    <FuelMoveDuration>785</FuelMoveDuration>
  </TFuelModuleDescriptor>
  <TFuelModuleDescriptor id="30400">
    <ControllerName>FuelController</ControllerName>
    <FuelCapacity>1500</FuelCapacity>
    <FuelMoveDuration>550</FuelMoveDuration>
  </TFuelModuleDescriptor>
  <TFuelModuleDescriptor id="30424">
    <ControllerName>FuelController</ControllerName>
    <FuelCapacity>1500</FuelCapacity>
    <FuelMoveDuration>750</FuelMoveDuration>
  </TFuelModuleDescriptor>
  <TFuelModuleDescriptor id="30549">
    <ControllerName>FuelController</ControllerName>
    <FuelCapacity>600</FuelCapacity>
    <FuelMoveDuration>440</FuelMoveDuration>
  </TFuelModuleDescriptor>
  <TFuelModuleDescriptor id="30584">
    <ControllerName>FuelController</ControllerName>
    <FuelCapacity>1000</FuelCapacity>
    <FuelMoveDuration>790</FuelMoveDuration>
  </TFuelModuleDescriptor>
  <TFuelModuleDescriptor id="30596">
    <ControllerName>FuelController</ControllerName>
    <FuelCapacity>600</FuelCapacity>
    <FuelMoveDuration>350</FuelMoveDuration>
  </TFuelModuleDescriptor>
  <TFuelModuleDescriptor id="30633">
    <ControllerName>FuelController</ControllerName>
    <FuelCapacity>1500</FuelCapacity>
    <FuelMoveDuration>950</FuelMoveDuration>
  </TFuelModuleDescriptor>
  <TFuelModuleDescriptor id="30802">
    <ControllerName>FuelController</ControllerName>
    <FuelCapacity>180</FuelCapacity>
    <FuelMoveDuration>430</FuelMoveDuration>
  </TFuelModuleDescriptor>
  <TFuelModuleDescriptor id="30827">
    <ControllerName>FuelController</ControllerName>
    <FuelCapacity>300</FuelCapacity>
    <FuelMoveDuration>540</FuelMoveDuration>
  </TFuelModuleDescriptor>
  <TFuelModuleDescriptor id="30895">
    <ControllerName>FuelController</ControllerName>
    <FuelCapacity>1000</FuelCapacity>
    <FuelMoveDuration>800</FuelMoveDuration>
  </TFuelModuleDescriptor>
  <TFuelModuleDescriptor id="30982">
    <ControllerName>FuelController</ControllerName>
    <FuelCapacity>1000</FuelCapacity>
    <FuelMoveDuration>540</FuelMoveDuration>
  </TFuelModuleDescriptor>
  <TFuelModuleDescriptor id="31077">
    <ControllerName>FuelController</ControllerName>
    <FuelCapacity>1720</FuelCapacity>
    <FuelMoveDuration>750</FuelMoveDuration>
  </TFuelModuleDescriptor>
  <TFuelModuleDescriptor id="31122">
    <ControllerName>FuelController</ControllerName>
    <FuelCapacity>1500</FuelCapacity>
    <FuelMoveDuration>400</FuelMoveDuration>
  </TFuelModuleDescriptor>
  <TFuelModuleDescriptor id="31149">
    <ControllerName>FuelController</ControllerName>
    <FuelCapacity>5000</FuelCapacity>
    <FuelMoveDuration>105</FuelMoveDuration>
  </TFuelModuleDescriptor>
  <TFuelModuleDescriptor id="31166">
    <ControllerName>FuelController</ControllerName>
    <FuelCapacity>3000</FuelCapacity>
    <FuelMoveDuration>105</FuelMoveDuration>
  </TFuelModuleDescriptor>
  <TFuelModuleDescriptor id="31178">
    <ControllerName>FuelController</ControllerName>
    <FuelCapacity>2000</FuelCapacity>
    <FuelMoveDuration>80</FuelMoveDuration>
  </TFuelModuleDescriptor>
  <TFuelModuleDescriptor id="31195">
    <ControllerName>FuelController</ControllerName>
    <FuelCapacity>2000</FuelCapacity>
    <FuelMoveDuration>85</FuelMoveDuration>
  </TFuelModuleDescriptor>
  <TFuelModuleDescriptor id="31211">
    <ControllerName>FuelController</ControllerName>
    <FuelCapacity>3000</FuelCapacity>
    <FuelMoveDuration>80</FuelMoveDuration>
  </TFuelModuleDescriptor>
  <TFuelModuleDescriptor id="31231">
    <ControllerName>FuelController</ControllerName>
    <FuelCapacity>3000</FuelCapacity>
    <FuelMoveDuration>85</FuelMoveDuration>
  </TFuelModuleDescriptor>
  <TFuelModuleDescriptor id="31283">
    <ControllerName>FuelController</ControllerName>
    <FuelCapacity>3000</FuelCapacity>
    <FuelMoveDuration>95</FuelMoveDuration>
  </TFuelModuleDescriptor>
  <TFuelModuleDescriptor id="31300">
    <ControllerName>FuelController</ControllerName>
    <FuelCapacity>4000</FuelCapacity>
    <FuelMoveDuration>90</FuelMoveDuration>
  </TFuelModuleDescriptor>
  <TFuelModuleDescriptor id="31309">
    <ControllerName>FuelController</ControllerName>
    <FuelCapacity>4000</FuelCapacity>
    <FuelMoveDuration>75</FuelMoveDuration>
  </TFuelModuleDescriptor>
  <TFuelModuleDescriptor id="31347">
    <ControllerName>FuelController</ControllerName>
    <FuelCapacity>2000</FuelCapacity>
    <FuelMoveDuration>95</FuelMoveDuration>
  </TFuelModuleDescriptor>
  <TFuelModuleDescriptor id="31365">
    <ControllerName>FuelController</ControllerName>
    <FuelCapacity>5000</FuelCapacity>
    <FuelMoveDuration>60</FuelMoveDuration>
  </TFuelModuleDescriptor>
  <TFuelModuleDescriptor id="31373">
    <ControllerName>FuelController</ControllerName>
    <FuelCapacity>3000</FuelCapacity>
    <FuelMoveDuration>65</FuelMoveDuration>
  </TFuelModuleDescriptor>
  <TFuelModuleDescriptor id="31430">
    <ControllerName>FuelController</ControllerName>
    <FuelCapacity>5000</FuelCapacity>
    <FuelMoveDuration>80</FuelMoveDuration>
  </TFuelModuleDescriptor>
  <TFuelModuleDescriptor id="31461">
    <ControllerName>FuelController</ControllerName>
    <FuelCapacity>6000</FuelCapacity>
    <FuelMoveDuration>90</FuelMoveDuration>
  </TFuelModuleDescriptor>
  <TFuelModuleDescriptor id="31490">
    <ControllerName>FuelController</ControllerName>
    <FuelCapacity>3000</FuelCapacity>
    <FuelMoveDuration>75</FuelMoveDuration>
  </TFuelModuleDescriptor>
  <TFuelModuleDescriptor id="31498">
    <ControllerName>FuelController</ControllerName>
    <FuelCapacity>3000</FuelCapacity>
    <FuelMoveDuration>90</FuelMoveDuration>
  </TFuelModuleDescriptor>
  <TFuelModuleDescriptor id="31536">
    <ControllerName>FuelController</ControllerName>
    <FuelCapacity>2000</FuelCapacity>
    <FuelMoveDuration>75</FuelMoveDuration>
  </TFuelModuleDescriptor>
  <TFuelModuleDescriptor id="31552">
    <ControllerName>FuelController</ControllerName>
    <FuelCapacity>5000</FuelCapacity>
    <FuelMoveDuration>85</FuelMoveDuration>
  </TFuelModuleDescriptor>
  <TFuelModuleDescriptor id="31560">
    <ControllerName>FuelController</ControllerName>
    <FuelCapacity>5000</FuelCapacity>
    <FuelMoveDuration>95</FuelMoveDuration>
  </TFuelModuleDescriptor>
  <TFuelModuleDescriptor id="31568">
    <ControllerName>FuelController</ControllerName>
    <FuelCapacity>5000</FuelCapacity>
    <FuelMoveDuration>75</FuelMoveDuration>
  </TFuelModuleDescriptor>
  <TFuelModuleDescriptor id="31626">
    <ControllerName>FuelController</ControllerName>
    <FuelCapacity>5000</FuelCapacity>
    <FuelMoveDuration>65</FuelMoveDuration>
  </TFuelModuleDescriptor>
  <TFuelModuleDescriptor id="31693">
    <ControllerName>FuelController</ControllerName>
    <FuelCapacity>4000</FuelCapacity>
    <FuelMoveDuration>95</FuelMoveDuration>
  </TFuelModuleDescriptor>
  <TFuelModuleDescriptor id="31800">
    <ControllerName>FuelController</ControllerName>
    <FuelCapacity>2000</FuelCapacity>
    <FuelMoveDuration>60</FuelMoveDuration>
  </TFuelModuleDescriptor>
  <TFuelModuleDescriptor id="31843">
    <ControllerName>FuelController</ControllerName>
    <FuelCapacity>3000</FuelCapacity>
    <FuelMoveDuration>100</FuelMoveDuration>
  </TFuelModuleDescriptor>
  <TFuelModuleDescriptor id="31873">
    <ControllerName>FuelController</ControllerName>
    <FuelCapacity>3000</FuelCapacity>
    <FuelMoveDuration>60</FuelMoveDuration>
  </TFuelModuleDescriptor>
  <TFuelModuleDescriptor id="32201">
    <ControllerName>FuelController</ControllerName>
    <FuelCapacity>4000</FuelCapacity>
    <FuelMoveDuration>60</FuelMoveDuration>
  </TFuelModuleDescriptor>
  <TFuelModuleDescriptor id="32330">
    <ControllerName>FuelController</ControllerName>
    <FuelCapacity>3000</FuelCapacity>
    <FuelMoveDuration>70</FuelMoveDuration>
  </TFuelModuleDescriptor>
</TFuelModuleDescriptors>