<?xml version="1.0" encoding="utf-8"?>
<TScannerConfigurationDescriptors>
  <TScannerConfigurationDescriptor id="27766">
    <ControllerName>ScannerConfigurationController</ControllerName>
    <UnitType>1</UnitType>
    <DetectionTBA>364000</DetectionTBA>
    <PorteeVision>260000</PorteeVision>
    <OpticalStrength>40</OpticalStrength>
    <OpticalStrengthAltitude>10</OpticalStrengthAltitude>
    <SpecializedOpticalStrengths>
      <collectionelement>Map: 6 : 40</collectionelement>
    </SpecializedOpticalStrengths>
    <SpecializedDetections>
      <collectionelement>Map: 4 : 416000</collectionelement>
      <collectionelement>Map: 6 : 1040000</collectionelement>
    </SpecializedDetections>
    <PorteeVisionTBA>null</PorteeVisionTBA>
    <OpticalStrengthAntiradar>null</OpticalStrengthAntiradar>
    <_ShortDatabaseName>null</_ShortDatabaseName>
  </TScannerConfigurationDescriptor>
  <TScannerConfigurationDescriptor id="27785">
    <ControllerName>ScannerConfigurationController</ControllerName>
    <UnitType>1</UnitType>
    <DetectionTBA>364000</DetectionTBA>
    <PorteeVision>260000</PorteeVision>
    <OpticalStrength>60</OpticalStrength>
    <OpticalStrengthAltitude>250</OpticalStrengthAltitude>
    <SpecializedOpticalStrengths>
      <collectionelement>Map: 6 : 60</collectionelement>
    </SpecializedOpticalStrengths>
    <SpecializedDetections>
      <collectionelement>Map: 4 : 780000</collectionelement>
      <collectionelement>Map: 6 : 1040000</collectionelement>
    </SpecializedDetections>
    <PorteeVisionTBA>null</PorteeVisionTBA>
    <OpticalStrengthAntiradar>null</OpticalStrengthAntiradar>
    <_ShortDatabaseName>null</_ShortDatabaseName>
  </TScannerConfigurationDescriptor>
  <TScannerConfigurationDescriptor id="27798">
    <ControllerName>ScannerConfigurationController</ControllerName>
    <UnitType>1</UnitType>
    <DetectionTBA>7800000</DetectionTBA>
    <PorteeVision>260000</PorteeVision>
    <OpticalStrength>60</OpticalStrength>
    <OpticalStrengthAltitude>250</OpticalStrengthAltitude>
    <SpecializedOpticalStrengths>
      <collectionelement>Map: 6 : 60</collectionelement>
    </SpecializedOpticalStrengths>
    <SpecializedDetections>
      <collectionelement>Map: 4 : 780000</collectionelement>
      <collectionelement>Map: 6 : 1040000</collectionelement>
    </SpecializedDetections>
    <PorteeVisionTBA>null</PorteeVisionTBA>
    <OpticalStrengthAntiradar>null</OpticalStrengthAntiradar>
    <_ShortDatabaseName>null</_ShortDatabaseName>
  </TScannerConfigurationDescriptor>
  <TScannerConfigurationDescriptor id="27813">
    <ControllerName>ScannerConfigurationController</ControllerName>
    <UnitType>1</UnitType>
    <DetectionTBA>364000</DetectionTBA>
    <PorteeVision>260000</PorteeVision>
    <OpticalStrength>80</OpticalStrength>
    <OpticalStrengthAltitude>40</OpticalStrengthAltitude>
    <SpecializedOpticalStrengths>
      <collectionelement>Map: 6 : 80</collectionelement>
    </SpecializedOpticalStrengths>
    <SpecializedDetections>
      <collectionelement>Map: 4 : 416000</collectionelement>
      <collectionelement>Map: 6 : 1040000</collectionelement>
    </SpecializedDetections>
    <PorteeVisionTBA>null</PorteeVisionTBA>
    <OpticalStrengthAntiradar>null</OpticalStrengthAntiradar>
    <_ShortDatabaseName>null</_ShortDatabaseName>
  </TScannerConfigurationDescriptor>
  <TScannerConfigurationDescriptor id="27901">
    <ControllerName>ScannerConfigurationController</ControllerName>
    <UnitType>1</UnitType>
    <DetectionTBA>364000</DetectionTBA>
    <PorteeVision>260000</PorteeVision>
    <OpticalStrength>170</OpticalStrength>
    <OpticalStrengthAltitude>40</OpticalStrengthAltitude>
    <SpecializedOpticalStrengths>
      <collectionelement>Map: 6 : 170</collectionelement>
    </SpecializedOpticalStrengths>
    <SpecializedDetections>
      <collectionelement>Map: 4 : 416000</collectionelement>
      <collectionelement>Map: 6 : 1040000</collectionelement>
    </SpecializedDetections>
    <PorteeVisionTBA>null</PorteeVisionTBA>
    <OpticalStrengthAntiradar>null</OpticalStrengthAntiradar>
    <_ShortDatabaseName>null</_ShortDatabaseName>
  </TScannerConfigurationDescriptor>
  <TScannerConfigurationDescriptor id="27931">
    <ControllerName>ScannerConfigurationController</ControllerName>
    <UnitType>1</UnitType>
    <DetectionTBA>364000</DetectionTBA>
    <PorteeVision>260000</PorteeVision>
    <OpticalStrength>60</OpticalStrength>
    <OpticalStrengthAltitude>120</OpticalStrengthAltitude>
    <SpecializedOpticalStrengths>
      <collectionelement>Map: 6 : 60</collectionelement>
    </SpecializedOpticalStrengths>
    <SpecializedDetections>
      <collectionelement>Map: 4 : 780000</collectionelement>
      <collectionelement>Map: 6 : 1040000</collectionelement>
    </SpecializedDetections>
    <PorteeVisionTBA>null</PorteeVisionTBA>
    <OpticalStrengthAntiradar>null</OpticalStrengthAntiradar>
    <_ShortDatabaseName>null</_ShortDatabaseName>
  </TScannerConfigurationDescriptor>
  <TScannerConfigurationDescriptor id="27985">
    <ControllerName>ScannerConfigurationController</ControllerName>
    <UnitType>1</UnitType>
    <DetectionTBA>364000</DetectionTBA>
    <PorteeVision>260000</PorteeVision>
    <OpticalStrength>60</OpticalStrength>
    <OpticalStrengthAltitude>10</OpticalStrengthAltitude>
    <SpecializedOpticalStrengths>
      <collectionelement>Map: 6 : 60</collectionelement>
    </SpecializedOpticalStrengths>
    <SpecializedDetections>
      <collectionelement>Map: 4 : 416000</collectionelement>
      <collectionelement>Map: 6 : 1040000</collectionelement>
    </SpecializedDetections>
    <PorteeVisionTBA>null</PorteeVisionTBA>
    <OpticalStrengthAntiradar>null</OpticalStrengthAntiradar>
    <_ShortDatabaseName>null</_ShortDatabaseName>
  </TScannerConfigurationDescriptor>
  <TScannerConfigurationDescriptor id="28001">
    <ControllerName>ScannerConfigurationController</ControllerName>
    <UnitType>1</UnitType>
    <DetectionTBA>364000</DetectionTBA>
    <PorteeVision>260000</PorteeVision>
    <OpticalStrength>120</OpticalStrength>
    <OpticalStrengthAltitude>40</OpticalStrengthAltitude>
    <SpecializedOpticalStrengths>
      <collectionelement>Map: 6 : 120</collectionelement>
    </SpecializedOpticalStrengths>
    <SpecializedDetections>
      <collectionelement>Map: 4 : 416000</collectionelement>
      <collectionelement>Map: 6 : 1040000</collectionelement>
    </SpecializedDetections>
    <PorteeVisionTBA>null</PorteeVisionTBA>
    <OpticalStrengthAntiradar>null</OpticalStrengthAntiradar>
    <_ShortDatabaseName>null</_ShortDatabaseName>
  </TScannerConfigurationDescriptor>
  <TScannerConfigurationDescriptor id="28010">
    <ControllerName>ScannerConfigurationController</ControllerName>
    <UnitType>1</UnitType>
    <DetectionTBA>364000</DetectionTBA>
    <PorteeVision>260000</PorteeVision>
    <OpticalStrength>60</OpticalStrength>
    <OpticalStrengthAltitude>20</OpticalStrengthAltitude>
    <SpecializedOpticalStrengths>
      <collectionelement>Map: 6 : 60</collectionelement>
    </SpecializedOpticalStrengths>
    <SpecializedDetections>
      <collectionelement>Map: 4 : 416000</collectionelement>
      <collectionelement>Map: 6 : 1040000</collectionelement>
    </SpecializedDetections>
    <PorteeVisionTBA>null</PorteeVisionTBA>
    <OpticalStrengthAntiradar>null</OpticalStrengthAntiradar>
    <_ShortDatabaseName>null</_ShortDatabaseName>
  </TScannerConfigurationDescriptor>
  <TScannerConfigurationDescriptor id="28043">
    <ControllerName>ScannerConfigurationController</ControllerName>
    <UnitType>1</UnitType>
    <DetectionTBA>364000</DetectionTBA>
    <PorteeVision>260000</PorteeVision>
    <OpticalStrength>60</OpticalStrength>
    <OpticalStrengthAltitude>40</OpticalStrengthAltitude>
    <SpecializedOpticalStrengths>
      <collectionelement>Map: 6 : 60</collectionelement>
    </SpecializedOpticalStrengths>
    <SpecializedDetections>
      <collectionelement>Map: 4 : 416000</collectionelement>
      <collectionelement>Map: 6 : 1040000</collectionelement>
    </SpecializedDetections>
    <PorteeVisionTBA>null</PorteeVisionTBA>
    <OpticalStrengthAntiradar>null</OpticalStrengthAntiradar>
    <_ShortDatabaseName>null</_ShortDatabaseName>
  </TScannerConfigurationDescriptor>
  <TScannerConfigurationDescriptor id="28066">
    <ControllerName>ScannerConfigurationController</ControllerName>
    <UnitType>1</UnitType>
    <DetectionTBA>364000</DetectionTBA>
    <PorteeVision>260000</PorteeVision>
    <OpticalStrength>80</OpticalStrength>
    <OpticalStrengthAltitude>20</OpticalStrengthAltitude>
    <SpecializedOpticalStrengths>
      <collectionelement>Map: 6 : 80</collectionelement>
    </SpecializedOpticalStrengths>
    <SpecializedDetections>
      <collectionelement>Map: 4 : 416000</collectionelement>
      <collectionelement>Map: 6 : 1040000</collectionelement>
    </SpecializedDetections>
    <PorteeVisionTBA>null</PorteeVisionTBA>
    <OpticalStrengthAntiradar>null</OpticalStrengthAntiradar>
    <_ShortDatabaseName>null</_ShortDatabaseName>
  </TScannerConfigurationDescriptor>
  <TScannerConfigurationDescriptor id="28223">
    <ControllerName>ScannerConfigurationController</ControllerName>
    <UnitType>1</UnitType>
    <DetectionTBA>364000</DetectionTBA>
    <PorteeVision>260000</PorteeVision>
    <OpticalStrength>80</OpticalStrength>
    <OpticalStrengthAltitude>80</OpticalStrengthAltitude>
    <SpecializedOpticalStrengths>
      <collectionelement>Map: 6 : 80</collectionelement>
    </SpecializedOpticalStrengths>
    <SpecializedDetections>
      <collectionelement>Map: 4 : 624000</collectionelement>
      <collectionelement>Map: 6 : 1040000</collectionelement>
    </SpecializedDetections>
    <PorteeVisionTBA>null</PorteeVisionTBA>
    <OpticalStrengthAntiradar>null</OpticalStrengthAntiradar>
    <_ShortDatabaseName>null</_ShortDatabaseName>
  </TScannerConfigurationDescriptor>
  <TScannerConfigurationDescriptor id="28287">
    <ControllerName>ScannerConfigurationController</ControllerName>
    <UnitType>1</UnitType>
    <DetectionTBA>364000</DetectionTBA>
    <PorteeVision>312000</PorteeVision>
    <OpticalStrength>220</OpticalStrength>
    <OpticalStrengthAltitude>40</OpticalStrengthAltitude>
    <SpecializedOpticalStrengths>
      <collectionelement>Map: 6 : 220</collectionelement>
    </SpecializedOpticalStrengths>
    <SpecializedDetections>
      <collectionelement>Map: 4 : 416000</collectionelement>
      <collectionelement>Map: 6 : 1040000</collectionelement>
    </SpecializedDetections>
    <PorteeVisionTBA>null</PorteeVisionTBA>
    <OpticalStrengthAntiradar>null</OpticalStrengthAntiradar>
    <_ShortDatabaseName>null</_ShortDatabaseName>
  </TScannerConfigurationDescriptor>
  <TScannerConfigurationDescriptor id="28717">
    <ControllerName>ScannerConfigurationController</ControllerName>
    <UnitType>1</UnitType>
    <DetectionTBA>364000</DetectionTBA>
    <PorteeVision>260000</PorteeVision>
    <OpticalStrength>120</OpticalStrength>
    <OpticalStrengthAltitude>20</OpticalStrengthAltitude>
    <SpecializedOpticalStrengths>
      <collectionelement>Map: 6 : 120</collectionelement>
    </SpecializedOpticalStrengths>
    <SpecializedDetections>
      <collectionelement>Map: 4 : 416000</collectionelement>
      <collectionelement>Map: 6 : 1040000</collectionelement>
    </SpecializedDetections>
    <PorteeVisionTBA>null</PorteeVisionTBA>
    <OpticalStrengthAntiradar>null</OpticalStrengthAntiradar>
    <_ShortDatabaseName>null</_ShortDatabaseName>
  </TScannerConfigurationDescriptor>
  <TScannerConfigurationDescriptor id="28724">
    <ControllerName>ScannerConfigurationController</ControllerName>
    <UnitType>1</UnitType>
    <DetectionTBA>364000</DetectionTBA>
    <PorteeVision>260000</PorteeVision>
    <OpticalStrength>120</OpticalStrength>
    <OpticalStrengthAltitude>80</OpticalStrengthAltitude>
    <SpecializedOpticalStrengths>
      <collectionelement>Map: 6 : 120</collectionelement>
    </SpecializedOpticalStrengths>
    <SpecializedDetections>
      <collectionelement>Map: 4 : 416000</collectionelement>
      <collectionelement>Map: 6 : 1040000</collectionelement>
    </SpecializedDetections>
    <PorteeVisionTBA>null</PorteeVisionTBA>
    <OpticalStrengthAntiradar>null</OpticalStrengthAntiradar>
    <_ShortDatabaseName>null</_ShortDatabaseName>
  </TScannerConfigurationDescriptor>
  <TScannerConfigurationDescriptor id="29910">
    <ControllerName>ScannerConfigurationController</ControllerName>
    <UnitType>1</UnitType>
    <DetectionTBA>364000</DetectionTBA>
    <PorteeVision>260000</PorteeVision>
    <OpticalStrength>40</OpticalStrength>
    <OpticalStrengthAltitude>20</OpticalStrengthAltitude>
    <SpecializedOpticalStrengths>
      <collectionelement>Map: 6 : 40</collectionelement>
    </SpecializedOpticalStrengths>
    <SpecializedDetections>
      <collectionelement>Map: 4 : 416000</collectionelement>
      <collectionelement>Map: 6 : 1040000</collectionelement>
    </SpecializedDetections>
    <PorteeVisionTBA>null</PorteeVisionTBA>
    <OpticalStrengthAntiradar>null</OpticalStrengthAntiradar>
    <_ShortDatabaseName>null</_ShortDatabaseName>
  </TScannerConfigurationDescriptor>
  <TScannerConfigurationDescriptor id="30204">
    <ControllerName>ScannerConfigurationController</ControllerName>
    <UnitType>1</UnitType>
    <DetectionTBA>364000</DetectionTBA>
    <PorteeVision>260000</PorteeVision>
    <OpticalStrength>40</OpticalStrength>
    <OpticalStrengthAltitude>40</OpticalStrengthAltitude>
    <SpecializedOpticalStrengths>
      <collectionelement>Map: 6 : 40</collectionelement>
    </SpecializedOpticalStrengths>
    <SpecializedDetections>
      <collectionelement>Map: 4 : 416000</collectionelement>
      <collectionelement>Map: 6 : 1040000</collectionelement>
    </SpecializedDetections>
    <PorteeVisionTBA>null</PorteeVisionTBA>
    <OpticalStrengthAntiradar>null</OpticalStrengthAntiradar>
    <_ShortDatabaseName>null</_ShortDatabaseName>
  </TScannerConfigurationDescriptor>
  <TScannerConfigurationDescriptor id="31240">
    <ControllerName>ScannerConfigurationController</ControllerName>
    <UnitType>1</UnitType>
    <DetectionTBA>364000</DetectionTBA>
    <PorteeVision>260000</PorteeVision>
    <OpticalStrength>80</OpticalStrength>
    <OpticalStrengthAltitude>250</OpticalStrengthAltitude>
    <SpecializedOpticalStrengths>
      <collectionelement>Map: 6 : 80</collectionelement>
    </SpecializedOpticalStrengths>
    <SpecializedDetections>
      <collectionelement>Map: 4 : 780000</collectionelement>
      <collectionelement>Map: 6 : 1040000</collectionelement>
    </SpecializedDetections>
    <PorteeVisionTBA>null</PorteeVisionTBA>
    <OpticalStrengthAntiradar>null</OpticalStrengthAntiradar>
    <_ShortDatabaseName>null</_ShortDatabaseName>
  </TScannerConfigurationDescriptor>
  <TScannerConfigurationDescriptor id="32635">
    <ControllerName>ScannerConfigurationController</ControllerName>
    <UnitType>1</UnitType>
    <DetectionTBA>364000</DetectionTBA>
    <PorteeVision>260000</PorteeVision>
    <OpticalStrength>60</OpticalStrength>
    <OpticalStrengthAltitude>80</OpticalStrengthAltitude>
    <SpecializedOpticalStrengths>
      <collectionelement>Map: 6 : 60</collectionelement>
    </SpecializedOpticalStrengths>
    <SpecializedDetections>
      <collectionelement>Map: 4 : 416000</collectionelement>
      <collectionelement>Map: 6 : 1040000</collectionelement>
    </SpecializedDetections>
    <PorteeVisionTBA>null</PorteeVisionTBA>
    <OpticalStrengthAntiradar>null</OpticalStrengthAntiradar>
    <_ShortDatabaseName>null</_ShortDatabaseName>
  </TScannerConfigurationDescriptor>
  <TScannerConfigurationDescriptor id="33032">
    <ControllerName>ScannerConfigurationController</ControllerName>
    <UnitType>1</UnitType>
    <DetectionTBA>364000</DetectionTBA>
    <PorteeVision>260000</PorteeVision>
    <OpticalStrength>80</OpticalStrength>
    <OpticalStrengthAltitude>80</OpticalStrengthAltitude>
    <SpecializedOpticalStrengths>
      <collectionelement>Map: 6 : 80</collectionelement>
    </SpecializedOpticalStrengths>
    <SpecializedDetections>
      <collectionelement>Map: 4 : 416000</collectionelement>
      <collectionelement>Map: 6 : 1040000</collectionelement>
    </SpecializedDetections>
    <PorteeVisionTBA>null</PorteeVisionTBA>
    <OpticalStrengthAntiradar>null</OpticalStrengthAntiradar>
    <_ShortDatabaseName>null</_ShortDatabaseName>
  </TScannerConfigurationDescriptor>
  <TScannerConfigurationDescriptor id="33038">
    <ControllerName>ScannerConfigurationController</ControllerName>
    <UnitType>1</UnitType>
    <DetectionTBA>364000</DetectionTBA>
    <PorteeVision>260000</PorteeVision>
    <OpticalStrength>170</OpticalStrength>
    <OpticalStrengthAltitude>80</OpticalStrengthAltitude>
    <SpecializedOpticalStrengths>
      <collectionelement>Map: 6 : 170</collectionelement>
    </SpecializedOpticalStrengths>
    <SpecializedDetections>
      <collectionelement>Map: 4 : 416000</collectionelement>
      <collectionelement>Map: 6 : 1040000</collectionelement>
    </SpecializedDetections>
    <PorteeVisionTBA>null</PorteeVisionTBA>
    <OpticalStrengthAntiradar>null</OpticalStrengthAntiradar>
    <_ShortDatabaseName>null</_ShortDatabaseName>
  </TScannerConfigurationDescriptor>
  <TScannerConfigurationDescriptor id="34003">
    <ControllerName>ScannerConfigurationController</ControllerName>
    <DetectionTBA>364000</DetectionTBA>
    <PorteeVision>260000</PorteeVision>
    <OpticalStrength>40</OpticalStrength>
    <OpticalStrengthAltitude>40</OpticalStrengthAltitude>
    <UnitType>null</UnitType>
    <SpecializedOpticalStrengths>null</SpecializedOpticalStrengths>
    <SpecializedDetections>null</SpecializedDetections>
    <PorteeVisionTBA>null</PorteeVisionTBA>
    <OpticalStrengthAntiradar>null</OpticalStrengthAntiradar>
    <_ShortDatabaseName>null</_ShortDatabaseName>
  </TScannerConfigurationDescriptor>
  <TScannerConfigurationDescriptor id="35142">
    <ControllerName>ScannerConfigurationController</ControllerName>
    <UnitType>6</UnitType>
    <DetectionTBA>364000</DetectionTBA>
    <PorteeVision>260000</PorteeVision>
    <OpticalStrength>60</OpticalStrength>
    <OpticalStrengthAltitude>20</OpticalStrengthAltitude>
    <SpecializedDetections>
      <collectionelement>Map: 4 : 416000</collectionelement>
    </SpecializedDetections>
    <SpecializedOpticalStrengths>null</SpecializedOpticalStrengths>
    <PorteeVisionTBA>null</PorteeVisionTBA>
    <OpticalStrengthAntiradar>null</OpticalStrengthAntiradar>
    <_ShortDatabaseName>null</_ShortDatabaseName>
  </TScannerConfigurationDescriptor>
  <TScannerConfigurationDescriptor id="35160">
    <ControllerName>ScannerConfigurationController</ControllerName>
    <UnitType>6</UnitType>
    <DetectionTBA>364000</DetectionTBA>
    <PorteeVision>364000</PorteeVision>
    <OpticalStrength>80</OpticalStrength>
    <OpticalStrengthAltitude>40</OpticalStrengthAltitude>
    <SpecializedOpticalStrengths>
      <collectionelement>Map: 6 : 80</collectionelement>
    </SpecializedOpticalStrengths>
    <SpecializedDetections>
      <collectionelement>Map: 4 : 780000</collectionelement>
      <collectionelement>Map: 6 : 1040000</collectionelement>
    </SpecializedDetections>
    <PorteeVisionTBA>null</PorteeVisionTBA>
    <OpticalStrengthAntiradar>null</OpticalStrengthAntiradar>
    <_ShortDatabaseName>null</_ShortDatabaseName>
  </TScannerConfigurationDescriptor>
  <TScannerConfigurationDescriptor id="35171">
    <ControllerName>ScannerConfigurationController</ControllerName>
    <UnitType>6</UnitType>
    <DetectionTBA>364000</DetectionTBA>
    <PorteeVision>364000</PorteeVision>
    <OpticalStrength>220</OpticalStrength>
    <OpticalStrengthAltitude>40</OpticalStrengthAltitude>
    <SpecializedOpticalStrengths>
      <collectionelement>Map: 6 : 80</collectionelement>
    </SpecializedOpticalStrengths>
    <SpecializedDetections>
      <collectionelement>Map: 4 : 780000</collectionelement>
      <collectionelement>Map: 6 : 1040000</collectionelement>
    </SpecializedDetections>
    <PorteeVisionTBA>null</PorteeVisionTBA>
    <OpticalStrengthAntiradar>null</OpticalStrengthAntiradar>
    <_ShortDatabaseName>null</_ShortDatabaseName>
  </TScannerConfigurationDescriptor>
  <TScannerConfigurationDescriptor id="35183">
    <ControllerName>ScannerConfigurationController</ControllerName>
    <UnitType>6</UnitType>
    <DetectionTBA>364000</DetectionTBA>
    <PorteeVision>364000</PorteeVision>
    <OpticalStrength>80</OpticalStrength>
    <OpticalStrengthAltitude>250</OpticalStrengthAltitude>
    <SpecializedOpticalStrengths>
      <collectionelement>Map: 6 : 80</collectionelement>
    </SpecializedOpticalStrengths>
    <SpecializedDetections>
      <collectionelement>Map: 4 : 780000</collectionelement>
      <collectionelement>Map: 6 : 1040000</collectionelement>
    </SpecializedDetections>
    <PorteeVisionTBA>null</PorteeVisionTBA>
    <OpticalStrengthAntiradar>null</OpticalStrengthAntiradar>
    <_ShortDatabaseName>null</_ShortDatabaseName>
  </TScannerConfigurationDescriptor>
  <TScannerConfigurationDescriptor id="35193">
    <ControllerName>ScannerConfigurationController</ControllerName>
    <UnitType>6</UnitType>
    <DetectionTBA>364000</DetectionTBA>
    <PorteeVision>364000</PorteeVision>
    <OpticalStrength>120</OpticalStrength>
    <OpticalStrengthAltitude>40</OpticalStrengthAltitude>
    <SpecializedOpticalStrengths>
      <collectionelement>Map: 6 : 120</collectionelement>
    </SpecializedOpticalStrengths>
    <SpecializedDetections>
      <collectionelement>Map: 4 : 780000</collectionelement>
      <collectionelement>Map: 6 : 1040000</collectionelement>
    </SpecializedDetections>
    <PorteeVisionTBA>null</PorteeVisionTBA>
    <OpticalStrengthAntiradar>null</OpticalStrengthAntiradar>
    <_ShortDatabaseName>null</_ShortDatabaseName>
  </TScannerConfigurationDescriptor>
  <TScannerConfigurationDescriptor id="35205">
    <ControllerName>ScannerConfigurationController</ControllerName>
    <UnitType>6</UnitType>
    <DetectionTBA>364000</DetectionTBA>
    <PorteeVision>364000</PorteeVision>
    <OpticalStrength>120</OpticalStrength>
    <OpticalStrengthAltitude>120</OpticalStrengthAltitude>
    <SpecializedOpticalStrengths>
      <collectionelement>Map: 6 : 220</collectionelement>
    </SpecializedOpticalStrengths>
    <SpecializedDetections>
      <collectionelement>Map: 4 : 780000</collectionelement>
      <collectionelement>Map: 6 : 1040000</collectionelement>
    </SpecializedDetections>
    <PorteeVisionTBA>null</PorteeVisionTBA>
    <OpticalStrengthAntiradar>null</OpticalStrengthAntiradar>
    <_ShortDatabaseName>null</_ShortDatabaseName>
  </TScannerConfigurationDescriptor>
  <TScannerConfigurationDescriptor id="35215">
    <ControllerName>ScannerConfigurationController</ControllerName>
    <UnitType>6</UnitType>
    <DetectionTBA>364000</DetectionTBA>
    <PorteeVision>364000</PorteeVision>
    <OpticalStrength>120</OpticalStrength>
    <OpticalStrengthAltitude>40</OpticalStrengthAltitude>
    <SpecializedOpticalStrengths>
      <collectionelement>Map: 6 : 80</collectionelement>
    </SpecializedOpticalStrengths>
    <SpecializedDetections>
      <collectionelement>Map: 4 : 780000</collectionelement>
      <collectionelement>Map: 6 : 1040000</collectionelement>
    </SpecializedDetections>
    <PorteeVisionTBA>null</PorteeVisionTBA>
    <OpticalStrengthAntiradar>null</OpticalStrengthAntiradar>
    <_ShortDatabaseName>null</_ShortDatabaseName>
  </TScannerConfigurationDescriptor>
  <TScannerConfigurationDescriptor id="35235">
    <ControllerName>ScannerConfigurationController</ControllerName>
    <UnitType>6</UnitType>
    <DetectionTBA>364000</DetectionTBA>
    <PorteeVision>364000</PorteeVision>
    <OpticalStrength>120</OpticalStrength>
    <OpticalStrengthAltitude>250</OpticalStrengthAltitude>
    <SpecializedOpticalStrengths>
      <collectionelement>Map: 6 : 220</collectionelement>
    </SpecializedOpticalStrengths>
    <SpecializedDetections>
      <collectionelement>Map: 4 : 780000</collectionelement>
      <collectionelement>Map: 6 : 1040000</collectionelement>
    </SpecializedDetections>
    <PorteeVisionTBA>null</PorteeVisionTBA>
    <OpticalStrengthAntiradar>null</OpticalStrengthAntiradar>
    <_ShortDatabaseName>null</_ShortDatabaseName>
  </TScannerConfigurationDescriptor>
  <TScannerConfigurationDescriptor id="35245">
    <ControllerName>ScannerConfigurationController</ControllerName>
    <UnitType>6</UnitType>
    <DetectionTBA>364000</DetectionTBA>
    <PorteeVision>260000</PorteeVision>
    <OpticalStrength>60</OpticalStrength>
    <OpticalStrengthAltitude>20</OpticalStrengthAltitude>
    <SpecializedDetections>
      <collectionelement>Map: 4 : 416000</collectionelement>
      <collectionelement>Map: 6 : 416000</collectionelement>
    </SpecializedDetections>
    <SpecializedOpticalStrengths>null</SpecializedOpticalStrengths>
    <PorteeVisionTBA>null</PorteeVisionTBA>
    <OpticalStrengthAntiradar>null</OpticalStrengthAntiradar>
    <_ShortDatabaseName>null</_ShortDatabaseName>
  </TScannerConfigurationDescriptor>
  <TScannerConfigurationDescriptor id="35262">
    <ControllerName>ScannerConfigurationController</ControllerName>
    <UnitType>6</UnitType>
    <DetectionTBA>364000</DetectionTBA>
    <PorteeVision>364000</PorteeVision>
    <OpticalStrength>120</OpticalStrength>
    <OpticalStrengthAltitude>160</OpticalStrengthAltitude>
    <SpecializedOpticalStrengths>
      <collectionelement>Map: 6 : 220</collectionelement>
    </SpecializedOpticalStrengths>
    <SpecializedDetections>
      <collectionelement>Map: 4 : 780000</collectionelement>
      <collectionelement>Map: 6 : 1040000</collectionelement>
    </SpecializedDetections>
    <PorteeVisionTBA>null</PorteeVisionTBA>
    <OpticalStrengthAntiradar>null</OpticalStrengthAntiradar>
    <_ShortDatabaseName>null</_ShortDatabaseName>
  </TScannerConfigurationDescriptor>
  <TScannerConfigurationDescriptor id="35280">
    <ControllerName>ScannerConfigurationController</ControllerName>
    <UnitType>6</UnitType>
    <DetectionTBA>364000</DetectionTBA>
    <PorteeVision>364000</PorteeVision>
    <OpticalStrength>120</OpticalStrength>
    <OpticalStrengthAltitude>80</OpticalStrengthAltitude>
    <SpecializedOpticalStrengths>
      <collectionelement>Map: 6 : 120</collectionelement>
    </SpecializedOpticalStrengths>
    <SpecializedDetections>
      <collectionelement>Map: 4 : 780000</collectionelement>
      <collectionelement>Map: 6 : 1040000</collectionelement>
    </SpecializedDetections>
    <PorteeVisionTBA>null</PorteeVisionTBA>
    <OpticalStrengthAntiradar>null</OpticalStrengthAntiradar>
    <_ShortDatabaseName>null</_ShortDatabaseName>
  </TScannerConfigurationDescriptor>
  <TScannerConfigurationDescriptor id="35300">
    <ControllerName>ScannerConfigurationController</ControllerName>
    <UnitType>6</UnitType>
    <DetectionTBA>364000</DetectionTBA>
    <PorteeVision>364000</PorteeVision>
    <OpticalStrength>120</OpticalStrength>
    <OpticalStrengthAltitude>160</OpticalStrengthAltitude>
    <SpecializedOpticalStrengths>
      <collectionelement>Map: 6 : 170</collectionelement>
    </SpecializedOpticalStrengths>
    <SpecializedDetections>
      <collectionelement>Map: 4 : 780000</collectionelement>
      <collectionelement>Map: 6 : 1040000</collectionelement>
    </SpecializedDetections>
    <PorteeVisionTBA>null</PorteeVisionTBA>
    <OpticalStrengthAntiradar>null</OpticalStrengthAntiradar>
    <_ShortDatabaseName>null</_ShortDatabaseName>
  </TScannerConfigurationDescriptor>
  <TScannerConfigurationDescriptor id="35320">
    <ControllerName>ScannerConfigurationController</ControllerName>
    <UnitType>6</UnitType>
    <DetectionTBA>364000</DetectionTBA>
    <PorteeVision>364000</PorteeVision>
    <OpticalStrength>170</OpticalStrength>
    <OpticalStrengthAltitude>40</OpticalStrengthAltitude>
    <SpecializedOpticalStrengths>
      <collectionelement>Map: 6 : 80</collectionelement>
    </SpecializedOpticalStrengths>
    <SpecializedDetections>
      <collectionelement>Map: 4 : 780000</collectionelement>
      <collectionelement>Map: 6 : 1040000</collectionelement>
    </SpecializedDetections>
    <PorteeVisionTBA>null</PorteeVisionTBA>
    <OpticalStrengthAntiradar>null</OpticalStrengthAntiradar>
    <_ShortDatabaseName>null</_ShortDatabaseName>
  </TScannerConfigurationDescriptor>
  <TScannerConfigurationDescriptor id="35327">
    <ControllerName>ScannerConfigurationController</ControllerName>
    <UnitType>6</UnitType>
    <DetectionTBA>364000</DetectionTBA>
    <PorteeVision>364000</PorteeVision>
    <OpticalStrength>120</OpticalStrength>
    <OpticalStrengthAltitude>160</OpticalStrengthAltitude>
    <SpecializedOpticalStrengths>
      <collectionelement>Map: 6 : 120</collectionelement>
    </SpecializedOpticalStrengths>
    <SpecializedDetections>
      <collectionelement>Map: 4 : 780000</collectionelement>
      <collectionelement>Map: 6 : 1040000</collectionelement>
    </SpecializedDetections>
    <PorteeVisionTBA>null</PorteeVisionTBA>
    <OpticalStrengthAntiradar>null</OpticalStrengthAntiradar>
    <_ShortDatabaseName>null</_ShortDatabaseName>
  </TScannerConfigurationDescriptor>
  <TScannerConfigurationDescriptor id="35347">
    <ControllerName>ScannerConfigurationController</ControllerName>
    <UnitType>6</UnitType>
    <DetectionTBA>364000</DetectionTBA>
    <PorteeVision>364000</PorteeVision>
    <OpticalStrength>120</OpticalStrength>
    <OpticalStrengthAltitude>40</OpticalStrengthAltitude>
    <SpecializedOpticalStrengths>
      <collectionelement>Map: 6 : 170</collectionelement>
    </SpecializedOpticalStrengths>
    <SpecializedDetections>
      <collectionelement>Map: 4 : 780000</collectionelement>
      <collectionelement>Map: 6 : 1040000</collectionelement>
    </SpecializedDetections>
    <PorteeVisionTBA>null</PorteeVisionTBA>
    <OpticalStrengthAntiradar>null</OpticalStrengthAntiradar>
    <_ShortDatabaseName>null</_ShortDatabaseName>
  </TScannerConfigurationDescriptor>
  <TScannerConfigurationDescriptor id="35357">
    <ControllerName>ScannerConfigurationController</ControllerName>
    <UnitType>6</UnitType>
    <DetectionTBA>364000</DetectionTBA>
    <PorteeVision>260000</PorteeVision>
    <OpticalStrength>60</OpticalStrength>
    <OpticalStrengthAltitude>40</OpticalStrengthAltitude>
    <SpecializedDetections>
      <collectionelement>Map: 4 : 416000</collectionelement>
    </SpecializedDetections>
    <SpecializedOpticalStrengths>null</SpecializedOpticalStrengths>
    <PorteeVisionTBA>null</PorteeVisionTBA>
    <OpticalStrengthAntiradar>null</OpticalStrengthAntiradar>
    <_ShortDatabaseName>null</_ShortDatabaseName>
  </TScannerConfigurationDescriptor>
  <TScannerConfigurationDescriptor id="35399">
    <ControllerName>ScannerConfigurationController</ControllerName>
    <UnitType>6</UnitType>
    <DetectionTBA>364000</DetectionTBA>
    <PorteeVision>364000</PorteeVision>
    <OpticalStrength>120</OpticalStrength>
    <OpticalStrengthAltitude>40</OpticalStrengthAltitude>
    <SpecializedOpticalStrengths>
      <collectionelement>Map: 6 : 220</collectionelement>
    </SpecializedOpticalStrengths>
    <SpecializedDetections>
      <collectionelement>Map: 4 : 780000</collectionelement>
      <collectionelement>Map: 6 : 1040000</collectionelement>
    </SpecializedDetections>
    <PorteeVisionTBA>null</PorteeVisionTBA>
    <OpticalStrengthAntiradar>null</OpticalStrengthAntiradar>
    <_ShortDatabaseName>null</_ShortDatabaseName>
  </TScannerConfigurationDescriptor>
  <TScannerConfigurationDescriptor id="35409">
    <ControllerName>ScannerConfigurationController</ControllerName>
    <UnitType>6</UnitType>
    <DetectionTBA>364000</DetectionTBA>
    <PorteeVision>364000</PorteeVision>
    <OpticalStrength>120</OpticalStrength>
    <OpticalStrengthAltitude>120</OpticalStrengthAltitude>
    <SpecializedOpticalStrengths>
      <collectionelement>Map: 6 : 170</collectionelement>
    </SpecializedOpticalStrengths>
    <SpecializedDetections>
      <collectionelement>Map: 4 : 780000</collectionelement>
      <collectionelement>Map: 6 : 1040000</collectionelement>
    </SpecializedDetections>
    <PorteeVisionTBA>null</PorteeVisionTBA>
    <OpticalStrengthAntiradar>null</OpticalStrengthAntiradar>
    <_ShortDatabaseName>null</_ShortDatabaseName>
  </TScannerConfigurationDescriptor>
  <TScannerConfigurationDescriptor id="35433">
    <ControllerName>ScannerConfigurationController</ControllerName>
    <UnitType>6</UnitType>
    <DetectionTBA>364000</DetectionTBA>
    <PorteeVision>364000</PorteeVision>
    <OpticalStrength>120</OpticalStrength>
    <OpticalStrengthAltitude>120</OpticalStrengthAltitude>
    <SpecializedOpticalStrengths>
      <collectionelement>Map: 6 : 120</collectionelement>
    </SpecializedOpticalStrengths>
    <SpecializedDetections>
      <collectionelement>Map: 4 : 780000</collectionelement>
      <collectionelement>Map: 6 : 1040000</collectionelement>
    </SpecializedDetections>
    <PorteeVisionTBA>null</PorteeVisionTBA>
    <OpticalStrengthAntiradar>null</OpticalStrengthAntiradar>
    <_ShortDatabaseName>null</_ShortDatabaseName>
  </TScannerConfigurationDescriptor>
  <TScannerConfigurationDescriptor id="35441">
    <ControllerName>ScannerConfigurationController</ControllerName>
    <UnitType>6</UnitType>
    <DetectionTBA>364000</DetectionTBA>
    <PorteeVision>364000</PorteeVision>
    <OpticalStrength>170</OpticalStrength>
    <OpticalStrengthAltitude>120</OpticalStrengthAltitude>
    <SpecializedOpticalStrengths>
      <collectionelement>Map: 6 : 80</collectionelement>
    </SpecializedOpticalStrengths>
    <SpecializedDetections>
      <collectionelement>Map: 4 : 780000</collectionelement>
      <collectionelement>Map: 6 : 1040000</collectionelement>
    </SpecializedDetections>
    <PorteeVisionTBA>null</PorteeVisionTBA>
    <OpticalStrengthAntiradar>null</OpticalStrengthAntiradar>
    <_ShortDatabaseName>null</_ShortDatabaseName>
  </TScannerConfigurationDescriptor>
  <TScannerConfigurationDescriptor id="35467">
    <ControllerName>ScannerConfigurationController</ControllerName>
    <PorteeVisionTBA>364000</PorteeVisionTBA>
    <DetectionTBA>416000</DetectionTBA>
    <PorteeVision>260000</PorteeVision>
    <SpecializedOpticalStrengths>
      <collectionelement>Map: 6 : 0</collectionelement>
    </SpecializedOpticalStrengths>
    <SpecializedDetections>
      <collectionelement>Map: 4 : 416000</collectionelement>
      <collectionelement>Map: 6 : 1040000</collectionelement>
    </SpecializedDetections>
    <UnitType>null</UnitType>
    <OpticalStrength>null</OpticalStrength>
    <OpticalStrengthAltitude>null</OpticalStrengthAltitude>
    <OpticalStrengthAntiradar>null</OpticalStrengthAntiradar>
    <_ShortDatabaseName>null</_ShortDatabaseName>
  </TScannerConfigurationDescriptor>
  <TScannerConfigurationDescriptor id="35479">
    <ControllerName>ScannerConfigurationController</ControllerName>
    <PorteeVisionTBA>364000</PorteeVisionTBA>
    <DetectionTBA>416000</DetectionTBA>
    <PorteeVision>260000</PorteeVision>
    <OpticalStrength>60</OpticalStrength>
    <OpticalStrengthAltitude>80</OpticalStrengthAltitude>
    <SpecializedOpticalStrengths>
      <collectionelement>Map: 6 : 60</collectionelement>
    </SpecializedOpticalStrengths>
    <SpecializedDetections>
      <collectionelement>Map: 4 : 416000</collectionelement>
      <collectionelement>Map: 6 : 1040000</collectionelement>
    </SpecializedDetections>
    <UnitType>null</UnitType>
    <OpticalStrengthAntiradar>null</OpticalStrengthAntiradar>
    <_ShortDatabaseName>null</_ShortDatabaseName>
  </TScannerConfigurationDescriptor>
  <TScannerConfigurationDescriptor id="35496">
    <ControllerName>ScannerConfigurationController</ControllerName>
    <PorteeVisionTBA>364000</PorteeVisionTBA>
    <DetectionTBA>416000</DetectionTBA>
    <PorteeVision>260000</PorteeVision>
    <OpticalStrength>60</OpticalStrength>
    <OpticalStrengthAltitude>170</OpticalStrengthAltitude>
    <SpecializedOpticalStrengths>
      <collectionelement>Map: 6 : 60</collectionelement>
    </SpecializedOpticalStrengths>
    <SpecializedDetections>
      <collectionelement>Map: 4 : 416000</collectionelement>
      <collectionelement>Map: 6 : 1040000</collectionelement>
    </SpecializedDetections>
    <UnitType>null</UnitType>
    <OpticalStrengthAntiradar>null</OpticalStrengthAntiradar>
    <_ShortDatabaseName>null</_ShortDatabaseName>
  </TScannerConfigurationDescriptor>
  <TScannerConfigurationDescriptor id="35527">
    <ControllerName>ScannerConfigurationController</ControllerName>
    <PorteeVisionTBA>364000</PorteeVisionTBA>
    <DetectionTBA>416000</DetectionTBA>
    <PorteeVision>260000</PorteeVision>
    <OpticalStrength>120</OpticalStrength>
    <OpticalStrengthAltitude>120</OpticalStrengthAltitude>
    <SpecializedOpticalStrengths>
      <collectionelement>Map: 6 : 120</collectionelement>
    </SpecializedOpticalStrengths>
    <SpecializedDetections>
      <collectionelement>Map: 4 : 520000</collectionelement>
      <collectionelement>Map: 6 : 1040000</collectionelement>
    </SpecializedDetections>
    <UnitType>null</UnitType>
    <OpticalStrengthAntiradar>null</OpticalStrengthAntiradar>
    <_ShortDatabaseName>null</_ShortDatabaseName>
  </TScannerConfigurationDescriptor>
  <TScannerConfigurationDescriptor id="35563">
    <ControllerName>ScannerConfigurationController</ControllerName>
    <PorteeVisionTBA>364000</PorteeVisionTBA>
    <DetectionTBA>416000</DetectionTBA>
    <PorteeVision>260000</PorteeVision>
    <OpticalStrength>80</OpticalStrength>
    <OpticalStrengthAltitude>80</OpticalStrengthAltitude>
    <SpecializedOpticalStrengths>
      <collectionelement>Map: 6 : 80</collectionelement>
    </SpecializedOpticalStrengths>
    <SpecializedDetections>
      <collectionelement>Map: 4 : 416000</collectionelement>
      <collectionelement>Map: 6 : 1040000</collectionelement>
    </SpecializedDetections>
    <UnitType>null</UnitType>
    <OpticalStrengthAntiradar>null</OpticalStrengthAntiradar>
    <_ShortDatabaseName>null</_ShortDatabaseName>
  </TScannerConfigurationDescriptor>
  <TScannerConfigurationDescriptor id="35572">
    <ControllerName>ScannerConfigurationController</ControllerName>
    <PorteeVisionTBA>364000</PorteeVisionTBA>
    <DetectionTBA>416000</DetectionTBA>
    <PorteeVision>260000</PorteeVision>
    <OpticalStrength>220</OpticalStrength>
    <OpticalStrengthAltitude>170</OpticalStrengthAltitude>
    <SpecializedOpticalStrengths>
      <collectionelement>Map: 6 : 220</collectionelement>
    </SpecializedOpticalStrengths>
    <SpecializedDetections>
      <collectionelement>Map: 4 : 520000</collectionelement>
      <collectionelement>Map: 6 : 1040000</collectionelement>
    </SpecializedDetections>
    <UnitType>null</UnitType>
    <OpticalStrengthAntiradar>null</OpticalStrengthAntiradar>
    <_ShortDatabaseName>null</_ShortDatabaseName>
  </TScannerConfigurationDescriptor>
  <TScannerConfigurationDescriptor id="35607">
    <ControllerName>ScannerConfigurationController</ControllerName>
    <PorteeVisionTBA>364000</PorteeVisionTBA>
    <DetectionTBA>416000</DetectionTBA>
    <PorteeVision>260000</PorteeVision>
    <OpticalStrength>60</OpticalStrength>
    <OpticalStrengthAltitude>80</OpticalStrengthAltitude>
    <SpecializedOpticalStrengths>
      <collectionelement>Map: 6 : 170</collectionelement>
    </SpecializedOpticalStrengths>
    <SpecializedDetections>
      <collectionelement>Map: 4 : 416000</collectionelement>
      <collectionelement>Map: 6 : 1040000</collectionelement>
    </SpecializedDetections>
    <UnitType>null</UnitType>
    <OpticalStrengthAntiradar>null</OpticalStrengthAntiradar>
    <_ShortDatabaseName>null</_ShortDatabaseName>
  </TScannerConfigurationDescriptor>
  <TScannerConfigurationDescriptor id="35621">
    <ControllerName>ScannerConfigurationController</ControllerName>
    <PorteeVisionTBA>364000</PorteeVisionTBA>
    <DetectionTBA>416000</DetectionTBA>
    <PorteeVision>260000</PorteeVision>
    <OpticalStrength>170</OpticalStrength>
    <OpticalStrengthAltitude>170</OpticalStrengthAltitude>
    <SpecializedOpticalStrengths>
      <collectionelement>Map: 6 : 170</collectionelement>
    </SpecializedOpticalStrengths>
    <SpecializedDetections>
      <collectionelement>Map: 4 : 520000</collectionelement>
      <collectionelement>Map: 6 : 1040000</collectionelement>
    </SpecializedDetections>
    <UnitType>null</UnitType>
    <OpticalStrengthAntiradar>null</OpticalStrengthAntiradar>
    <_ShortDatabaseName>null</_ShortDatabaseName>
  </TScannerConfigurationDescriptor>
  <TScannerConfigurationDescriptor id="35644">
    <ControllerName>ScannerConfigurationController</ControllerName>
    <PorteeVisionTBA>364000</PorteeVisionTBA>
    <DetectionTBA>416000</DetectionTBA>
    <PorteeVision>260000</PorteeVision>
    <OpticalStrength>60</OpticalStrength>
    <OpticalStrengthAltitude>80</OpticalStrengthAltitude>
    <SpecializedOpticalStrengths>
      <collectionelement>Map: 6 : 220</collectionelement>
    </SpecializedOpticalStrengths>
    <SpecializedDetections>
      <collectionelement>Map: 4 : 416000</collectionelement>
      <collectionelement>Map: 6 : 1040000</collectionelement>
    </SpecializedDetections>
    <UnitType>null</UnitType>
    <OpticalStrengthAntiradar>null</OpticalStrengthAntiradar>
    <_ShortDatabaseName>null</_ShortDatabaseName>
  </TScannerConfigurationDescriptor>
  <TScannerConfigurationDescriptor id="35800">
    <ControllerName>ScannerConfigurationController</ControllerName>
    <PorteeVisionTBA>364000</PorteeVisionTBA>
    <DetectionTBA>416000</DetectionTBA>
    <PorteeVision>260000</PorteeVision>
    <OpticalStrength>170</OpticalStrength>
    <OpticalStrengthAltitude>170</OpticalStrengthAltitude>
    <SpecializedOpticalStrengths>
      <collectionelement>Map: 6 : 170</collectionelement>
    </SpecializedOpticalStrengths>
    <SpecializedDetections>
      <collectionelement>Map: 4 : 416000</collectionelement>
      <collectionelement>Map: 6 : 1040000</collectionelement>
    </SpecializedDetections>
    <UnitType>null</UnitType>
    <OpticalStrengthAntiradar>null</OpticalStrengthAntiradar>
    <_ShortDatabaseName>null</_ShortDatabaseName>
  </TScannerConfigurationDescriptor>
  <TScannerConfigurationDescriptor id="35914">
    <ControllerName>ScannerConfigurationController</ControllerName>
    <PorteeVisionTBA>364000</PorteeVisionTBA>
    <DetectionTBA>416000</DetectionTBA>
    <PorteeVision>260000</PorteeVision>
    <OpticalStrength>80</OpticalStrength>
    <OpticalStrengthAltitude>170</OpticalStrengthAltitude>
    <SpecializedOpticalStrengths>
      <collectionelement>Map: 6 : 80</collectionelement>
    </SpecializedOpticalStrengths>
    <SpecializedDetections>
      <collectionelement>Map: 4 : 416000</collectionelement>
      <collectionelement>Map: 6 : 1040000</collectionelement>
    </SpecializedDetections>
    <UnitType>null</UnitType>
    <OpticalStrengthAntiradar>null</OpticalStrengthAntiradar>
    <_ShortDatabaseName>null</_ShortDatabaseName>
  </TScannerConfigurationDescriptor>
  <TScannerConfigurationDescriptor id="35922">
    <ControllerName>ScannerConfigurationController</ControllerName>
    <PorteeVisionTBA>364000</PorteeVisionTBA>
    <DetectionTBA>416000</DetectionTBA>
    <PorteeVision>260000</PorteeVision>
    <OpticalStrength>220</OpticalStrength>
    <OpticalStrengthAltitude>170</OpticalStrengthAltitude>
    <OpticalStrengthAntiradar>300</OpticalStrengthAntiradar>
    <SpecializedOpticalStrengths>
      <collectionelement>Map: 6 : 220</collectionelement>
    </SpecializedOpticalStrengths>
    <SpecializedDetections>
      <collectionelement>Map: 4 : 520000</collectionelement>
      <collectionelement>Map: 6 : 1040000</collectionelement>
    </SpecializedDetections>
    <UnitType>null</UnitType>
    <_ShortDatabaseName>null</_ShortDatabaseName>
  </TScannerConfigurationDescriptor>
  <TScannerConfigurationDescriptor id="35979">
    <ControllerName>ScannerConfigurationController</ControllerName>
    <PorteeVisionTBA>364000</PorteeVisionTBA>
    <DetectionTBA>416000</DetectionTBA>
    <PorteeVision>260000</PorteeVision>
    <OpticalStrength>60</OpticalStrength>
    <OpticalStrengthAltitude>80</OpticalStrengthAltitude>
    <SpecializedOpticalStrengths>
      <collectionelement>Map: 6 : 120</collectionelement>
    </SpecializedOpticalStrengths>
    <SpecializedDetections>
      <collectionelement>Map: 4 : 416000</collectionelement>
      <collectionelement>Map: 6 : 1040000</collectionelement>
    </SpecializedDetections>
    <UnitType>null</UnitType>
    <OpticalStrengthAntiradar>null</OpticalStrengthAntiradar>
    <_ShortDatabaseName>null</_ShortDatabaseName>
  </TScannerConfigurationDescriptor>
  <TScannerConfigurationDescriptor id="36726">
    <ControllerName>ScannerConfigurationController</ControllerName>
    <UnitType>4</UnitType>
    <PorteeVisionTBA>364000</PorteeVisionTBA>
    <DetectionTBA>364000</DetectionTBA>
    <PorteeVision>260000</PorteeVision>
    <OpticalStrengthAltitude>150</OpticalStrengthAltitude>
    <SpecializedOpticalStrengths>
      <collectionelement>Map: 6 : 60</collectionelement>
    </SpecializedOpticalStrengths>
    <SpecializedDetections>
      <collectionelement>Map: 4 : 2340000</collectionelement>
      <collectionelement>Map: 6 : 520000</collectionelement>
    </SpecializedDetections>
    <OpticalStrength>null</OpticalStrength>
    <OpticalStrengthAntiradar>null</OpticalStrengthAntiradar>
    <_ShortDatabaseName>null</_ShortDatabaseName>
  </TScannerConfigurationDescriptor>
  <TScannerConfigurationDescriptor id="36779">
    <ControllerName>ScannerConfigurationController</ControllerName>
    <UnitType>4</UnitType>
    <PorteeVisionTBA>364000</PorteeVisionTBA>
    <DetectionTBA>364000</DetectionTBA>
    <PorteeVision>338000</PorteeVision>
    <OpticalStrengthAltitude>150</OpticalStrengthAltitude>
    <OpticalStrengthAntiradar>500</OpticalStrengthAntiradar>
    <SpecializedOpticalStrengths>
      <collectionelement>Map: 6 : 60</collectionelement>
    </SpecializedOpticalStrengths>
    <SpecializedDetections>
      <collectionelement>Map: 4 : 2340000</collectionelement>
      <collectionelement>Map: 6 : 520000</collectionelement>
    </SpecializedDetections>
    <OpticalStrength>null</OpticalStrength>
    <_ShortDatabaseName>null</_ShortDatabaseName>
  </TScannerConfigurationDescriptor>
  <TScannerConfigurationDescriptor id="36805">
    <ControllerName>ScannerConfigurationController</ControllerName>
    <UnitType>4</UnitType>
    <PorteeVisionTBA>364000</PorteeVisionTBA>
    <DetectionTBA>364000</DetectionTBA>
    <PorteeVision>260000</PorteeVision>
    <OpticalStrengthAltitude>150</OpticalStrengthAltitude>
    <SpecializedOpticalStrengths>
      <collectionelement>Map: 6 : 60</collectionelement>
    </SpecializedOpticalStrengths>
    <SpecializedDetections>
      <collectionelement>Map: 4 : 2340000</collectionelement>
      <collectionelement>Map: 6 : 1040000</collectionelement>
    </SpecializedDetections>
    <OpticalStrength>null</OpticalStrength>
    <OpticalStrengthAntiradar>null</OpticalStrengthAntiradar>
    <_ShortDatabaseName>null</_ShortDatabaseName>
  </TScannerConfigurationDescriptor>
  <TScannerConfigurationDescriptor id="36838">
    <ControllerName>ScannerConfigurationController</ControllerName>
    <UnitType>4</UnitType>
    <PorteeVisionTBA>364000</PorteeVisionTBA>
    <DetectionTBA>364000</DetectionTBA>
    <PorteeVision>260000</PorteeVision>
    <OpticalStrengthAltitude>300</OpticalStrengthAltitude>
    <SpecializedOpticalStrengths>
      <collectionelement>Map: 6 : 60</collectionelement>
    </SpecializedOpticalStrengths>
    <SpecializedDetections>
      <collectionelement>Map: 4 : 2340000</collectionelement>
      <collectionelement>Map: 6 : 520000</collectionelement>
    </SpecializedDetections>
    <OpticalStrength>null</OpticalStrength>
    <OpticalStrengthAntiradar>null</OpticalStrengthAntiradar>
    <_ShortDatabaseName>null</_ShortDatabaseName>
  </TScannerConfigurationDescriptor>
  <TScannerConfigurationDescriptor id="36883">
    <ControllerName>ScannerConfigurationController</ControllerName>
    <UnitType>4</UnitType>
    <PorteeVisionTBA>364000</PorteeVisionTBA>
    <DetectionTBA>364000</DetectionTBA>
    <PorteeVision>260000</PorteeVision>
    <OpticalStrengthAltitude>450</OpticalStrengthAltitude>
    <SpecializedOpticalStrengths>
      <collectionelement>Map: 6 : 60</collectionelement>
    </SpecializedOpticalStrengths>
    <SpecializedDetections>
      <collectionelement>Map: 4 : 2340000</collectionelement>
      <collectionelement>Map: 6 : 520000</collectionelement>
    </SpecializedDetections>
    <OpticalStrength>null</OpticalStrength>
    <OpticalStrengthAntiradar>null</OpticalStrengthAntiradar>
    <_ShortDatabaseName>null</_ShortDatabaseName>
  </TScannerConfigurationDescriptor>
  <TScannerConfigurationDescriptor id="36892">
    <ControllerName>ScannerConfigurationController</ControllerName>
    <UnitType>4</UnitType>
    <PorteeVisionTBA>364000</PorteeVisionTBA>
    <DetectionTBA>364000</DetectionTBA>
    <PorteeVision>260000</PorteeVision>
    <OpticalStrengthAltitude>300</OpticalStrengthAltitude>
    <SpecializedOpticalStrengths>
      <collectionelement>Map: 6 : 60</collectionelement>
    </SpecializedOpticalStrengths>
    <SpecializedDetections>
      <collectionelement>Map: 4 : 2340000</collectionelement>
      <collectionelement>Map: 6 : 1040000</collectionelement>
    </SpecializedDetections>
    <OpticalStrength>null</OpticalStrength>
    <OpticalStrengthAntiradar>null</OpticalStrengthAntiradar>
    <_ShortDatabaseName>null</_ShortDatabaseName>
  </TScannerConfigurationDescriptor>
  <TScannerConfigurationDescriptor id="36950">
    <ControllerName>ScannerConfigurationController</ControllerName>
    <UnitType>4</UnitType>
    <PorteeVisionTBA>364000</PorteeVisionTBA>
    <DetectionTBA>364000</DetectionTBA>
    <PorteeVision>390000</PorteeVision>
    <OpticalStrengthAltitude>150</OpticalStrengthAltitude>
    <OpticalStrengthAntiradar>500</OpticalStrengthAntiradar>
    <SpecializedOpticalStrengths>
      <collectionelement>Map: 6 : 60</collectionelement>
    </SpecializedOpticalStrengths>
    <SpecializedDetections>
      <collectionelement>Map: 4 : 2340000</collectionelement>
      <collectionelement>Map: 6 : 520000</collectionelement>
    </SpecializedDetections>
    <OpticalStrength>null</OpticalStrength>
    <_ShortDatabaseName>null</_ShortDatabaseName>
  </TScannerConfigurationDescriptor>
  <TScannerConfigurationDescriptor id="36959">
    <ControllerName>ScannerConfigurationController</ControllerName>
    <UnitType>4</UnitType>
    <PorteeVisionTBA>364000</PorteeVisionTBA>
    <DetectionTBA>364000</DetectionTBA>
    <PorteeVision>416000</PorteeVision>
    <OpticalStrengthAltitude>150</OpticalStrengthAltitude>
    <OpticalStrengthAntiradar>500</OpticalStrengthAntiradar>
    <SpecializedOpticalStrengths>
      <collectionelement>Map: 6 : 60</collectionelement>
    </SpecializedOpticalStrengths>
    <SpecializedDetections>
      <collectionelement>Map: 4 : 2340000</collectionelement>
      <collectionelement>Map: 6 : 520000</collectionelement>
    </SpecializedDetections>
    <OpticalStrength>null</OpticalStrength>
    <_ShortDatabaseName>null</_ShortDatabaseName>
  </TScannerConfigurationDescriptor>
  <TScannerConfigurationDescriptor id="37059">
    <ControllerName>ScannerConfigurationController</ControllerName>
    <UnitType>4</UnitType>
    <PorteeVisionTBA>364000</PorteeVisionTBA>
    <DetectionTBA>364000</DetectionTBA>
    <PorteeVision>260000</PorteeVision>
    <OpticalStrengthAltitude>900</OpticalStrengthAltitude>
    <SpecializedOpticalStrengths>
      <collectionelement>Map: 6 : 60</collectionelement>
    </SpecializedOpticalStrengths>
    <SpecializedDetections>
      <collectionelement>Map: 4 : 2340000</collectionelement>
      <collectionelement>Map: 6 : 520000</collectionelement>
    </SpecializedDetections>
    <OpticalStrength>null</OpticalStrength>
    <OpticalStrengthAntiradar>null</OpticalStrengthAntiradar>
    <_ShortDatabaseName>null</_ShortDatabaseName>
  </TScannerConfigurationDescriptor>
  <TScannerConfigurationDescriptor id="37167">
    <ControllerName>ScannerConfigurationController</ControllerName>
    <UnitType>4</UnitType>
    <PorteeVisionTBA>364000</PorteeVisionTBA>
    <DetectionTBA>364000</DetectionTBA>
    <PorteeVision>260000</PorteeVision>
    <OpticalStrengthAltitude>450</OpticalStrengthAltitude>
    <SpecializedOpticalStrengths>
      <collectionelement>Map: 6 : 60</collectionelement>
    </SpecializedOpticalStrengths>
    <SpecializedDetections>
      <collectionelement>Map: 4 : 2340000</collectionelement>
      <collectionelement>Map: 6 : 364000</collectionelement>
    </SpecializedDetections>
    <OpticalStrength>null</OpticalStrength>
    <OpticalStrengthAntiradar>null</OpticalStrengthAntiradar>
    <_ShortDatabaseName>null</_ShortDatabaseName>
  </TScannerConfigurationDescriptor>
  <TScannerConfigurationDescriptor id="37288">
    <ControllerName>ScannerConfigurationController</ControllerName>
    <UnitType>4</UnitType>
    <PorteeVisionTBA>364000</PorteeVisionTBA>
    <DetectionTBA>364000</DetectionTBA>
    <PorteeVision>390000</PorteeVision>
    <OpticalStrengthAltitude>300</OpticalStrengthAltitude>
    <OpticalStrengthAntiradar>500</OpticalStrengthAntiradar>
    <SpecializedOpticalStrengths>
      <collectionelement>Map: 6 : 60</collectionelement>
    </SpecializedOpticalStrengths>
    <SpecializedDetections>
      <collectionelement>Map: 4 : 2340000</collectionelement>
      <collectionelement>Map: 6 : 520000</collectionelement>
    </SpecializedDetections>
    <OpticalStrength>null</OpticalStrength>
    <_ShortDatabaseName>null</_ShortDatabaseName>
  </TScannerConfigurationDescriptor>
  <TScannerConfigurationDescriptor id="37345">
    <ControllerName>ScannerConfigurationController</ControllerName>
    <UnitType>4</UnitType>
    <PorteeVisionTBA>364000</PorteeVisionTBA>
    <DetectionTBA>364000</DetectionTBA>
    <PorteeVision>338000</PorteeVision>
    <OpticalStrengthAltitude>300</OpticalStrengthAltitude>
    <OpticalStrengthAntiradar>500</OpticalStrengthAntiradar>
    <SpecializedOpticalStrengths>
      <collectionelement>Map: 6 : 60</collectionelement>
    </SpecializedOpticalStrengths>
    <SpecializedDetections>
      <collectionelement>Map: 4 : 2340000</collectionelement>
      <collectionelement>Map: 6 : 520000</collectionelement>
    </SpecializedDetections>
    <OpticalStrength>null</OpticalStrength>
    <_ShortDatabaseName>null</_ShortDatabaseName>
  </TScannerConfigurationDescriptor>
  <TScannerConfigurationDescriptor id="37423">
    <ControllerName>ScannerConfigurationController</ControllerName>
    <UnitType>4</UnitType>
    <PorteeVisionTBA>364000</PorteeVisionTBA>
    <DetectionTBA>364000</DetectionTBA>
    <PorteeVision>260000</PorteeVision>
    <OpticalStrengthAltitude>450</OpticalStrengthAltitude>
    <SpecializedOpticalStrengths>
      <collectionelement>Map: 6 : 60</collectionelement>
    </SpecializedOpticalStrengths>
    <SpecializedDetections>
      <collectionelement>Map: 4 : 2340000</collectionelement>
      <collectionelement>Map: 6 : 1040000</collectionelement>
    </SpecializedDetections>
    <OpticalStrength>null</OpticalStrength>
    <OpticalStrengthAntiradar>null</OpticalStrengthAntiradar>
    <_ShortDatabaseName>null</_ShortDatabaseName>
  </TScannerConfigurationDescriptor>
  <TScannerConfigurationDescriptor id="37529">
    <ControllerName>ScannerConfigurationController</ControllerName>
    <UnitType>4</UnitType>
    <PorteeVisionTBA>364000</PorteeVisionTBA>
    <DetectionTBA>364000</DetectionTBA>
    <PorteeVision>416000</PorteeVision>
    <OpticalStrengthAltitude>450</OpticalStrengthAltitude>
    <OpticalStrengthAntiradar>500</OpticalStrengthAntiradar>
    <SpecializedOpticalStrengths>
      <collectionelement>Map: 6 : 60</collectionelement>
    </SpecializedOpticalStrengths>
    <SpecializedDetections>
      <collectionelement>Map: 4 : 2340000</collectionelement>
      <collectionelement>Map: 6 : 520000</collectionelement>
    </SpecializedDetections>
    <OpticalStrength>null</OpticalStrength>
    <_ShortDatabaseName>null</_ShortDatabaseName>
  </TScannerConfigurationDescriptor>
  <TScannerConfigurationDescriptor id="37551">
    <ControllerName>ScannerConfigurationController</ControllerName>
    <UnitType>4</UnitType>
    <PorteeVisionTBA>364000</PorteeVisionTBA>
    <DetectionTBA>364000</DetectionTBA>
    <PorteeVision>364000</PorteeVision>
    <OpticalStrengthAltitude>150</OpticalStrengthAltitude>
    <OpticalStrengthAntiradar>500</OpticalStrengthAntiradar>
    <SpecializedOpticalStrengths>
      <collectionelement>Map: 6 : 60</collectionelement>
    </SpecializedOpticalStrengths>
    <SpecializedDetections>
      <collectionelement>Map: 4 : 2340000</collectionelement>
      <collectionelement>Map: 6 : 520000</collectionelement>
    </SpecializedDetections>
    <OpticalStrength>null</OpticalStrength>
    <_ShortDatabaseName>null</_ShortDatabaseName>
  </TScannerConfigurationDescriptor>
  <TScannerConfigurationDescriptor id="37608">
    <ControllerName>ScannerConfigurationController</ControllerName>
    <UnitType>4</UnitType>
    <PorteeVisionTBA>364000</PorteeVisionTBA>
    <DetectionTBA>364000</DetectionTBA>
    <PorteeVision>260000</PorteeVision>
    <OpticalStrengthAltitude>150</OpticalStrengthAltitude>
    <SpecializedOpticalStrengths>
      <collectionelement>Map: 6 : 60</collectionelement>
    </SpecializedOpticalStrengths>
    <SpecializedDetections>
      <collectionelement>Map: 4 : 2340000</collectionelement>
      <collectionelement>Map: 6 : 364000</collectionelement>
    </SpecializedDetections>
    <OpticalStrength>null</OpticalStrength>
    <OpticalStrengthAntiradar>null</OpticalStrengthAntiradar>
    <_ShortDatabaseName>null</_ShortDatabaseName>
  </TScannerConfigurationDescriptor>
  <TScannerConfigurationDescriptor id="38379">
    <ControllerName>ScannerConfigurationController</ControllerName>
    <UnitType>null</UnitType>
    <DetectionTBA>null</DetectionTBA>
    <PorteeVision>null</PorteeVision>
    <OpticalStrength>null</OpticalStrength>
    <OpticalStrengthAltitude>null</OpticalStrengthAltitude>
    <SpecializedOpticalStrengths>null</SpecializedOpticalStrengths>
    <SpecializedDetections>null</SpecializedDetections>
    <PorteeVisionTBA>null</PorteeVisionTBA>
    <OpticalStrengthAntiradar>null</OpticalStrengthAntiradar>
    <_ShortDatabaseName>null</_ShortDatabaseName>
  </TScannerConfigurationDescriptor>
  <TScannerConfigurationDescriptor id="93448">
    <ControllerName>ScannerConfigurationController</ControllerName>
    <UnitType>1</UnitType>
    <DetectionTBA>624000</DetectionTBA>
    <PorteeVision>312000</PorteeVision>
    <SpecializedOpticalStrengths>
      <collectionelement>Map: 6 : 0</collectionelement>
    </SpecializedOpticalStrengths>
    <SpecializedDetections>
      <collectionelement>Map: 4 : 416000</collectionelement>
      <collectionelement>Map: 6 : 1040000</collectionelement>
    </SpecializedDetections>
    <OpticalStrength>null</OpticalStrength>
    <OpticalStrengthAltitude>null</OpticalStrengthAltitude>
    <PorteeVisionTBA>null</PorteeVisionTBA>
    <OpticalStrengthAntiradar>null</OpticalStrengthAntiradar>
    <_ShortDatabaseName>null</_ShortDatabaseName>
  </TScannerConfigurationDescriptor>
  <TScannerConfigurationDescriptor id="93819">
    <_ShortDatabaseName>ScannerConfigurationDescriptor</_ShortDatabaseName>
    <ControllerName>ScannerConfigurationController</ControllerName>
    <UnitType>null</UnitType>
    <DetectionTBA>null</DetectionTBA>
    <PorteeVision>null</PorteeVision>
    <OpticalStrength>null</OpticalStrength>
    <OpticalStrengthAltitude>null</OpticalStrengthAltitude>
    <SpecializedOpticalStrengths>null</SpecializedOpticalStrengths>
    <SpecializedDetections>null</SpecializedDetections>
    <PorteeVisionTBA>null</PorteeVisionTBA>
    <OpticalStrengthAntiradar>null</OpticalStrengthAntiradar>
  </TScannerConfigurationDescriptor>
</TScannerConfigurationDescriptors>