<?xml version="1.0" encoding="utf-8"?>
<TBlindagePropertiess>
  <TBlindageProperties id="45502">
    <ArmorDescriptorFront>202 : 62898 (True) - TArmorDescriptor</ArmorDescriptorFront>
    <ArmorDescriptorSides>202 : 62899 (True) - TArmorDescriptor</ArmorDescriptorSides>
    <ArmorDescriptorRear>202 : 62899 (True) - TArmorDescriptor</ArmorDescriptorRear>
    <ArmorDescriptorTop>202 : 62899 (True) - TArmorDescriptor</ArmorDescriptorTop>
  </TBlindageProperties>
  <TBlindageProperties id="45531">
    <ArmorDescriptorFront>202 : 62899 (True) - TArmorDescriptor</ArmorDescriptorFront>
    <ArmorDescriptorSides>202 : 62899 (True) - TArmorDescriptor</ArmorDescriptorSides>
    <ArmorDescriptorRear>202 : 62899 (True) - TArmorDescriptor</ArmorDescriptorRear>
    <ArmorDescriptorTop>202 : 62899 (True) - TArmorDescriptor</ArmorDescriptorTop>
  </TBlindageProperties>
  <TBlindageProperties id="45588">
    <ArmorDescriptorFront>202 : 62961 (True) - TArmorDescriptor</ArmorDescriptorFront>
    <ArmorDescriptorSides>202 : 62962 (True) - TArmorDescriptor</ArmorDescriptorSides>
    <ArmorDescriptorRear>202 : 62898 (True) - TArmorDescriptor</ArmorDescriptorRear>
    <ArmorDescriptorTop>202 : 62898 (True) - TArmorDescriptor</ArmorDescriptorTop>
  </TBlindageProperties>
  <TBlindageProperties id="45658">
    <ArmorDescriptorFront>202 : 62898 (True) - TArmorDescriptor</ArmorDescriptorFront>
    <ArmorDescriptorSides>202 : 62899 (True) - TArmorDescriptor</ArmorDescriptorSides>
    <ArmorDescriptorRear>202 : 62899 (True) - TArmorDescriptor</ArmorDescriptorRear>
    <ArmorDescriptorTop>202 : 63011 (True) - TArmorDescriptor</ArmorDescriptorTop>
  </TBlindageProperties>
  <TBlindageProperties id="45694">
    <ArmorDescriptorFront>202 : 63034 (True) - TArmorDescriptor</ArmorDescriptorFront>
    <ArmorDescriptorSides>202 : 63034 (True) - TArmorDescriptor</ArmorDescriptorSides>
    <ArmorDescriptorRear>202 : 63034 (True) - TArmorDescriptor</ArmorDescriptorRear>
    <ArmorDescriptorTop>202 : 63034 (True) - TArmorDescriptor</ArmorDescriptorTop>
  </TBlindageProperties>
  <TBlindageProperties id="45734">
    <ArmorDescriptorFront>202 : 63011 (True) - TArmorDescriptor</ArmorDescriptorFront>
    <ArmorDescriptorSides>202 : 63011 (True) - TArmorDescriptor</ArmorDescriptorSides>
    <ArmorDescriptorRear>202 : 63011 (True) - TArmorDescriptor</ArmorDescriptorRear>
    <ArmorDescriptorTop>202 : 63011 (True) - TArmorDescriptor</ArmorDescriptorTop>
  </TBlindageProperties>
  <TBlindageProperties id="45822">
    <ArmorDescriptorFront>202 : 63132 (True) - TArmorDescriptor</ArmorDescriptorFront>
    <ArmorDescriptorSides>202 : 62962 (True) - TArmorDescriptor</ArmorDescriptorSides>
    <ArmorDescriptorRear>202 : 62898 (True) - TArmorDescriptor</ArmorDescriptorRear>
    <ArmorDescriptorTop>202 : 62898 (True) - TArmorDescriptor</ArmorDescriptorTop>
  </TBlindageProperties>
  <TBlindageProperties id="45888">
    <ArmorDescriptorFront>202 : 62898 (True) - TArmorDescriptor</ArmorDescriptorFront>
    <ArmorDescriptorSides>202 : 62898 (True) - TArmorDescriptor</ArmorDescriptorSides>
    <ArmorDescriptorRear>202 : 62899 (True) - TArmorDescriptor</ArmorDescriptorRear>
    <ArmorDescriptorTop>202 : 62899 (True) - TArmorDescriptor</ArmorDescriptorTop>
  </TBlindageProperties>
  <TBlindageProperties id="45930">
    <ArmorDescriptorFront>202 : 62962 (True) - TArmorDescriptor</ArmorDescriptorFront>
    <ArmorDescriptorSides>202 : 62962 (True) - TArmorDescriptor</ArmorDescriptorSides>
    <ArmorDescriptorRear>202 : 62899 (True) - TArmorDescriptor</ArmorDescriptorRear>
    <ArmorDescriptorTop>202 : 62899 (True) - TArmorDescriptor</ArmorDescriptorTop>
  </TBlindageProperties>
  <TBlindageProperties id="45977">
    <ArmorDescriptorFront>202 : 63226 (True) - TArmorDescriptor</ArmorDescriptorFront>
    <ArmorDescriptorSides>202 : 62962 (True) - TArmorDescriptor</ArmorDescriptorSides>
    <ArmorDescriptorRear>202 : 62898 (True) - TArmorDescriptor</ArmorDescriptorRear>
    <ArmorDescriptorTop>202 : 62899 (True) - TArmorDescriptor</ArmorDescriptorTop>
  </TBlindageProperties>
  <TBlindageProperties id="45992">
    <ArmorDescriptorFront>202 : 63234 (True) - TArmorDescriptor</ArmorDescriptorFront>
    <ArmorDescriptorSides>202 : 63132 (True) - TArmorDescriptor</ArmorDescriptorSides>
    <ArmorDescriptorRear>202 : 62898 (True) - TArmorDescriptor</ArmorDescriptorRear>
    <ArmorDescriptorTop>202 : 62898 (True) - TArmorDescriptor</ArmorDescriptorTop>
  </TBlindageProperties>
  <TBlindageProperties id="46017">
    <ArmorDescriptorFront>202 : 63247 (True) - TArmorDescriptor</ArmorDescriptorFront>
    <ArmorDescriptorSides>202 : 62961 (True) - TArmorDescriptor</ArmorDescriptorSides>
    <ArmorDescriptorRear>202 : 62898 (True) - TArmorDescriptor</ArmorDescriptorRear>
    <ArmorDescriptorTop>202 : 62898 (True) - TArmorDescriptor</ArmorDescriptorTop>
  </TBlindageProperties>
  <TBlindageProperties id="46027">
    <ArmorDescriptorFront>202 : 62962 (True) - TArmorDescriptor</ArmorDescriptorFront>
    <ArmorDescriptorSides>202 : 62898 (True) - TArmorDescriptor</ArmorDescriptorSides>
    <ArmorDescriptorRear>202 : 62898 (True) - TArmorDescriptor</ArmorDescriptorRear>
    <ArmorDescriptorTop>202 : 62899 (True) - TArmorDescriptor</ArmorDescriptorTop>
  </TBlindageProperties>
  <TBlindageProperties id="46050">
    <ArmorDescriptorFront>202 : 63265 (True) - TArmorDescriptor</ArmorDescriptorFront>
    <ArmorDescriptorSides>202 : 63132 (True) - TArmorDescriptor</ArmorDescriptorSides>
    <ArmorDescriptorRear>202 : 62962 (True) - TArmorDescriptor</ArmorDescriptorRear>
    <ArmorDescriptorTop>202 : 62898 (True) - TArmorDescriptor</ArmorDescriptorTop>
  </TBlindageProperties>
  <TBlindageProperties id="46064">
    <ArmorDescriptorFront>202 : 63271 (True) - TArmorDescriptor</ArmorDescriptorFront>
    <ArmorDescriptorSides>202 : 63226 (True) - TArmorDescriptor</ArmorDescriptorSides>
    <ArmorDescriptorRear>202 : 62962 (True) - TArmorDescriptor</ArmorDescriptorRear>
    <ArmorDescriptorTop>202 : 62898 (True) - TArmorDescriptor</ArmorDescriptorTop>
  </TBlindageProperties>
  <TBlindageProperties id="46076">
    <ArmorDescriptorFront>202 : 62962 (True) - TArmorDescriptor</ArmorDescriptorFront>
    <ArmorDescriptorSides>202 : 62898 (True) - TArmorDescriptor</ArmorDescriptorSides>
    <ArmorDescriptorRear>202 : 62899 (True) - TArmorDescriptor</ArmorDescriptorRear>
    <ArmorDescriptorTop>202 : 62898 (True) - TArmorDescriptor</ArmorDescriptorTop>
  </TBlindageProperties>
  <TBlindageProperties id="46085">
    <ArmorDescriptorFront>202 : 62899 (True) - TArmorDescriptor</ArmorDescriptorFront>
    <ArmorDescriptorSides>202 : 62899 (True) - TArmorDescriptor</ArmorDescriptorSides>
    <ArmorDescriptorRear>202 : 62899 (True) - TArmorDescriptor</ArmorDescriptorRear>
    <ArmorDescriptorTop>202 : 63011 (True) - TArmorDescriptor</ArmorDescriptorTop>
  </TBlindageProperties>
  <TBlindageProperties id="46463">
    <ArmorDescriptorFront>202 : 62899 (True) - TArmorDescriptor</ArmorDescriptorFront>
    <ArmorDescriptorSides>202 : 63011 (True) - TArmorDescriptor</ArmorDescriptorSides>
    <ArmorDescriptorRear>202 : 63011 (True) - TArmorDescriptor</ArmorDescriptorRear>
    <ArmorDescriptorTop>202 : 63011 (True) - TArmorDescriptor</ArmorDescriptorTop>
  </TBlindageProperties>
  <TBlindageProperties id="46589">
    <ArmorDescriptorFront>202 : 62962 (True) - TArmorDescriptor</ArmorDescriptorFront>
    <ArmorDescriptorSides>202 : 62898 (True) - TArmorDescriptor</ArmorDescriptorSides>
    <ArmorDescriptorRear>202 : 62899 (True) - TArmorDescriptor</ArmorDescriptorRear>
    <ArmorDescriptorTop>202 : 62899 (True) - TArmorDescriptor</ArmorDescriptorTop>
  </TBlindageProperties>
  <TBlindageProperties id="46671">
    <ArmorDescriptorFront>202 : 62962 (True) - TArmorDescriptor</ArmorDescriptorFront>
    <ArmorDescriptorSides>202 : 62962 (True) - TArmorDescriptor</ArmorDescriptorSides>
    <ArmorDescriptorRear>202 : 62898 (True) - TArmorDescriptor</ArmorDescriptorRear>
    <ArmorDescriptorTop>202 : 62899 (True) - TArmorDescriptor</ArmorDescriptorTop>
  </TBlindageProperties>
  <TBlindageProperties id="46706">
    <ArmorDescriptorFront>202 : 63667 (True) - TArmorDescriptor</ArmorDescriptorFront>
    <ArmorDescriptorSides>202 : 63668 (True) - TArmorDescriptor</ArmorDescriptorSides>
    <ArmorDescriptorRear>202 : 62898 (True) - TArmorDescriptor</ArmorDescriptorRear>
    <ArmorDescriptorTop>202 : 62898 (True) - TArmorDescriptor</ArmorDescriptorTop>
  </TBlindageProperties>
  <TBlindageProperties id="47053">
    <ArmorDescriptorFront>202 : 63234 (True) - TArmorDescriptor</ArmorDescriptorFront>
    <ArmorDescriptorSides>202 : 62962 (True) - TArmorDescriptor</ArmorDescriptorSides>
    <ArmorDescriptorRear>202 : 62898 (True) - TArmorDescriptor</ArmorDescriptorRear>
    <ArmorDescriptorTop>202 : 62898 (True) - TArmorDescriptor</ArmorDescriptorTop>
  </TBlindageProperties>
  <TBlindageProperties id="47152">
    <ArmorDescriptorFront>202 : 62898 (True) - TArmorDescriptor</ArmorDescriptorFront>
    <ArmorDescriptorSides>202 : 62898 (True) - TArmorDescriptor</ArmorDescriptorSides>
    <ArmorDescriptorRear>202 : 62899 (True) - TArmorDescriptor</ArmorDescriptorRear>
    <ArmorDescriptorTop>202 : 63011 (True) - TArmorDescriptor</ArmorDescriptorTop>
  </TBlindageProperties>
  <TBlindageProperties id="47365">
    <ArmorDescriptorFront>202 : 64038 (True) - TArmorDescriptor</ArmorDescriptorFront>
    <ArmorDescriptorSides>202 : 62961 (True) - TArmorDescriptor</ArmorDescriptorSides>
    <ArmorDescriptorRear>202 : 62898 (True) - TArmorDescriptor</ArmorDescriptorRear>
    <ArmorDescriptorTop>202 : 62898 (True) - TArmorDescriptor</ArmorDescriptorTop>
  </TBlindageProperties>
  <TBlindageProperties id="47428">
    <ArmorDescriptorFront>202 : 64074 (True) - TArmorDescriptor</ArmorDescriptorFront>
    <ArmorDescriptorSides>202 : 62961 (True) - TArmorDescriptor</ArmorDescriptorSides>
    <ArmorDescriptorRear>202 : 63132 (True) - TArmorDescriptor</ArmorDescriptorRear>
    <ArmorDescriptorTop>202 : 62962 (True) - TArmorDescriptor</ArmorDescriptorTop>
  </TBlindageProperties>
  <TBlindageProperties id="47449">
    <ArmorDescriptorFront>202 : 63226 (True) - TArmorDescriptor</ArmorDescriptorFront>
    <ArmorDescriptorSides>202 : 62962 (True) - TArmorDescriptor</ArmorDescriptorSides>
    <ArmorDescriptorRear>202 : 62898 (True) - TArmorDescriptor</ArmorDescriptorRear>
    <ArmorDescriptorTop>202 : 62898 (True) - TArmorDescriptor</ArmorDescriptorTop>
  </TBlindageProperties>
  <TBlindageProperties id="47468">
    <ArmorDescriptorFront>202 : 62898 (True) - TArmorDescriptor</ArmorDescriptorFront>
    <ArmorDescriptorSides>202 : 62898 (True) - TArmorDescriptor</ArmorDescriptorSides>
    <ArmorDescriptorRear>202 : 62898 (True) - TArmorDescriptor</ArmorDescriptorRear>
    <ArmorDescriptorTop>202 : 62898 (True) - TArmorDescriptor</ArmorDescriptorTop>
  </TBlindageProperties>
  <TBlindageProperties id="47532">
    <ArmorDescriptorFront>202 : 63234 (True) - TArmorDescriptor</ArmorDescriptorFront>
    <ArmorDescriptorSides>202 : 63132 (True) - TArmorDescriptor</ArmorDescriptorSides>
    <ArmorDescriptorRear>202 : 62898 (True) - TArmorDescriptor</ArmorDescriptorRear>
    <ArmorDescriptorTop>202 : 62899 (True) - TArmorDescriptor</ArmorDescriptorTop>
  </TBlindageProperties>
  <TBlindageProperties id="47641">
    <ArmorDescriptorFront>202 : 64074 (True) - TArmorDescriptor</ArmorDescriptorFront>
    <ArmorDescriptorSides>202 : 63668 (True) - TArmorDescriptor</ArmorDescriptorSides>
    <ArmorDescriptorRear>202 : 63132 (True) - TArmorDescriptor</ArmorDescriptorRear>
    <ArmorDescriptorTop>202 : 62962 (True) - TArmorDescriptor</ArmorDescriptorTop>
  </TBlindageProperties>
  <TBlindageProperties id="47655">
    <ArmorDescriptorFront>202 : 63226 (True) - TArmorDescriptor</ArmorDescriptorFront>
    <ArmorDescriptorSides>202 : 63132 (True) - TArmorDescriptor</ArmorDescriptorSides>
    <ArmorDescriptorRear>202 : 62898 (True) - TArmorDescriptor</ArmorDescriptorRear>
    <ArmorDescriptorTop>202 : 62899 (True) - TArmorDescriptor</ArmorDescriptorTop>
  </TBlindageProperties>
  <TBlindageProperties id="47689">
    <ArmorDescriptorFront>202 : 63668 (True) - TArmorDescriptor</ArmorDescriptorFront>
    <ArmorDescriptorSides>202 : 62962 (True) - TArmorDescriptor</ArmorDescriptorSides>
    <ArmorDescriptorRear>202 : 62898 (True) - TArmorDescriptor</ArmorDescriptorRear>
    <ArmorDescriptorTop>202 : 62898 (True) - TArmorDescriptor</ArmorDescriptorTop>
  </TBlindageProperties>
  <TBlindageProperties id="47700">
    <ArmorDescriptorFront>202 : 63667 (True) - TArmorDescriptor</ArmorDescriptorFront>
    <ArmorDescriptorSides>202 : 63226 (True) - TArmorDescriptor</ArmorDescriptorSides>
    <ArmorDescriptorRear>202 : 63132 (True) - TArmorDescriptor</ArmorDescriptorRear>
    <ArmorDescriptorTop>202 : 62962 (True) - TArmorDescriptor</ArmorDescriptorTop>
  </TBlindageProperties>
  <TBlindageProperties id="47711">
    <ArmorDescriptorFront>202 : 62961 (True) - TArmorDescriptor</ArmorDescriptorFront>
    <ArmorDescriptorSides>202 : 62962 (True) - TArmorDescriptor</ArmorDescriptorSides>
    <ArmorDescriptorRear>202 : 62899 (True) - TArmorDescriptor</ArmorDescriptorRear>
    <ArmorDescriptorTop>202 : 62899 (True) - TArmorDescriptor</ArmorDescriptorTop>
  </TBlindageProperties>
  <TBlindageProperties id="47732">
    <ArmorDescriptorFront>202 : 64038 (True) - TArmorDescriptor</ArmorDescriptorFront>
    <ArmorDescriptorSides>202 : 63132 (True) - TArmorDescriptor</ArmorDescriptorSides>
    <ArmorDescriptorRear>202 : 62898 (True) - TArmorDescriptor</ArmorDescriptorRear>
    <ArmorDescriptorTop>202 : 62898 (True) - TArmorDescriptor</ArmorDescriptorTop>
  </TBlindageProperties>
  <TBlindageProperties id="47745">
    <ArmorDescriptorFront>202 : 63271 (True) - TArmorDescriptor</ArmorDescriptorFront>
    <ArmorDescriptorSides>202 : 63132 (True) - TArmorDescriptor</ArmorDescriptorSides>
    <ArmorDescriptorRear>202 : 62898 (True) - TArmorDescriptor</ArmorDescriptorRear>
    <ArmorDescriptorTop>202 : 62898 (True) - TArmorDescriptor</ArmorDescriptorTop>
  </TBlindageProperties>
  <TBlindageProperties id="47755">
    <ArmorDescriptorFront>202 : 63234 (True) - TArmorDescriptor</ArmorDescriptorFront>
    <ArmorDescriptorSides>202 : 62962 (True) - TArmorDescriptor</ArmorDescriptorSides>
    <ArmorDescriptorRear>202 : 62898 (True) - TArmorDescriptor</ArmorDescriptorRear>
    <ArmorDescriptorTop>202 : 62899 (True) - TArmorDescriptor</ArmorDescriptorTop>
  </TBlindageProperties>
  <TBlindageProperties id="47768">
    <ArmorDescriptorFront>202 : 63247 (True) - TArmorDescriptor</ArmorDescriptorFront>
    <ArmorDescriptorSides>202 : 63226 (True) - TArmorDescriptor</ArmorDescriptorSides>
    <ArmorDescriptorRear>202 : 62962 (True) - TArmorDescriptor</ArmorDescriptorRear>
    <ArmorDescriptorTop>202 : 62898 (True) - TArmorDescriptor</ArmorDescriptorTop>
  </TBlindageProperties>
  <TBlindageProperties id="47792">
    <ArmorDescriptorFront>202 : 64306 (True) - TArmorDescriptor</ArmorDescriptorFront>
    <ArmorDescriptorSides>202 : 64038 (True) - TArmorDescriptor</ArmorDescriptorSides>
    <ArmorDescriptorRear>202 : 62962 (True) - TArmorDescriptor</ArmorDescriptorRear>
    <ArmorDescriptorTop>202 : 62962 (True) - TArmorDescriptor</ArmorDescriptorTop>
  </TBlindageProperties>
  <TBlindageProperties id="47978">
    <ArmorDescriptorFront>202 : 64413 (True) - TArmorDescriptor</ArmorDescriptorFront>
    <ArmorDescriptorSides>202 : 63265 (True) - TArmorDescriptor</ArmorDescriptorSides>
    <ArmorDescriptorRear>202 : 63226 (True) - TArmorDescriptor</ArmorDescriptorRear>
    <ArmorDescriptorTop>202 : 63132 (True) - TArmorDescriptor</ArmorDescriptorTop>
  </TBlindageProperties>
  <TBlindageProperties id="47989">
    <ArmorDescriptorFront>202 : 64420 (True) - TArmorDescriptor</ArmorDescriptorFront>
    <ArmorDescriptorSides>202 : 63247 (True) - TArmorDescriptor</ArmorDescriptorSides>
    <ArmorDescriptorRear>202 : 63226 (True) - TArmorDescriptor</ArmorDescriptorRear>
    <ArmorDescriptorTop>202 : 63132 (True) - TArmorDescriptor</ArmorDescriptorTop>
  </TBlindageProperties>
  <TBlindageProperties id="47998">
    <ArmorDescriptorFront>202 : 63667 (True) - TArmorDescriptor</ArmorDescriptorFront>
    <ArmorDescriptorSides>202 : 63226 (True) - TArmorDescriptor</ArmorDescriptorSides>
    <ArmorDescriptorRear>202 : 62962 (True) - TArmorDescriptor</ArmorDescriptorRear>
    <ArmorDescriptorTop>202 : 62898 (True) - TArmorDescriptor</ArmorDescriptorTop>
  </TBlindageProperties>
  <TBlindageProperties id="48019">
    <ArmorDescriptorFront>202 : 64306 (True) - TArmorDescriptor</ArmorDescriptorFront>
    <ArmorDescriptorSides>202 : 63247 (True) - TArmorDescriptor</ArmorDescriptorSides>
    <ArmorDescriptorRear>202 : 63226 (True) - TArmorDescriptor</ArmorDescriptorRear>
    <ArmorDescriptorTop>202 : 63132 (True) - TArmorDescriptor</ArmorDescriptorTop>
  </TBlindageProperties>
  <TBlindageProperties id="48061">
    <ArmorDescriptorFront>202 : 63247 (True) - TArmorDescriptor</ArmorDescriptorFront>
    <ArmorDescriptorSides>202 : 63132 (True) - TArmorDescriptor</ArmorDescriptorSides>
    <ArmorDescriptorRear>202 : 62898 (True) - TArmorDescriptor</ArmorDescriptorRear>
    <ArmorDescriptorTop>202 : 62898 (True) - TArmorDescriptor</ArmorDescriptorTop>
  </TBlindageProperties>
  <TBlindageProperties id="48092">
    <ArmorDescriptorFront>202 : 63247 (True) - TArmorDescriptor</ArmorDescriptorFront>
    <ArmorDescriptorSides>202 : 63226 (True) - TArmorDescriptor</ArmorDescriptorSides>
    <ArmorDescriptorRear>202 : 62962 (True) - TArmorDescriptor</ArmorDescriptorRear>
    <ArmorDescriptorTop>202 : 62962 (True) - TArmorDescriptor</ArmorDescriptorTop>
  </TBlindageProperties>
  <TBlindageProperties id="48103">
    <ArmorDescriptorFront>202 : 63247 (True) - TArmorDescriptor</ArmorDescriptorFront>
    <ArmorDescriptorSides>202 : 63226 (True) - TArmorDescriptor</ArmorDescriptorSides>
    <ArmorDescriptorRear>202 : 63132 (True) - TArmorDescriptor</ArmorDescriptorRear>
    <ArmorDescriptorTop>202 : 62962 (True) - TArmorDescriptor</ArmorDescriptorTop>
  </TBlindageProperties>
  <TBlindageProperties id="48114">
    <ArmorDescriptorFront>202 : 64306 (True) - TArmorDescriptor</ArmorDescriptorFront>
    <ArmorDescriptorSides>202 : 63271 (True) - TArmorDescriptor</ArmorDescriptorSides>
    <ArmorDescriptorRear>202 : 63226 (True) - TArmorDescriptor</ArmorDescriptorRear>
    <ArmorDescriptorTop>202 : 62962 (True) - TArmorDescriptor</ArmorDescriptorTop>
  </TBlindageProperties>
  <TBlindageProperties id="48126">
    <ArmorDescriptorFront>202 : 63271 (True) - TArmorDescriptor</ArmorDescriptorFront>
    <ArmorDescriptorSides>202 : 63234 (True) - TArmorDescriptor</ArmorDescriptorSides>
    <ArmorDescriptorRear>202 : 62898 (True) - TArmorDescriptor</ArmorDescriptorRear>
    <ArmorDescriptorTop>202 : 62898 (True) - TArmorDescriptor</ArmorDescriptorTop>
  </TBlindageProperties>
  <TBlindageProperties id="48138">
    <ArmorDescriptorFront>202 : 63668 (True) - TArmorDescriptor</ArmorDescriptorFront>
    <ArmorDescriptorSides>202 : 62961 (True) - TArmorDescriptor</ArmorDescriptorSides>
    <ArmorDescriptorRear>202 : 62898 (True) - TArmorDescriptor</ArmorDescriptorRear>
    <ArmorDescriptorTop>202 : 62899 (True) - TArmorDescriptor</ArmorDescriptorTop>
  </TBlindageProperties>
  <TBlindageProperties id="48232">
    <ArmorDescriptorFront>202 : 62899 (True) - TArmorDescriptor</ArmorDescriptorFront>
    <ArmorDescriptorSides>202 : 62899 (True) - TArmorDescriptor</ArmorDescriptorSides>
    <ArmorDescriptorRear>202 : 63011 (True) - TArmorDescriptor</ArmorDescriptorRear>
    <ArmorDescriptorTop>202 : 63011 (True) - TArmorDescriptor</ArmorDescriptorTop>
  </TBlindageProperties>
  <TBlindageProperties id="48456">
    <ArmorDescriptorFront>202 : 63226 (True) - TArmorDescriptor</ArmorDescriptorFront>
    <ArmorDescriptorSides>202 : 62961 (True) - TArmorDescriptor</ArmorDescriptorSides>
    <ArmorDescriptorRear>202 : 62898 (True) - TArmorDescriptor</ArmorDescriptorRear>
    <ArmorDescriptorTop>202 : 62898 (True) - TArmorDescriptor</ArmorDescriptorTop>
  </TBlindageProperties>
  <TBlindageProperties id="48685">
    <ArmorDescriptorFront>202 : 62961 (True) - TArmorDescriptor</ArmorDescriptorFront>
    <ArmorDescriptorSides>202 : 62962 (True) - TArmorDescriptor</ArmorDescriptorSides>
    <ArmorDescriptorRear>202 : 62898 (True) - TArmorDescriptor</ArmorDescriptorRear>
    <ArmorDescriptorTop>202 : 63011 (True) - TArmorDescriptor</ArmorDescriptorTop>
  </TBlindageProperties>
  <TBlindageProperties id="49305">
    <ArmorDescriptorFront>202 : 65223 (True) - TArmorDescriptor</ArmorDescriptorFront>
    <ArmorDescriptorSides>202 : 64038 (True) - TArmorDescriptor</ArmorDescriptorSides>
    <ArmorDescriptorRear>202 : 62961 (True) - TArmorDescriptor</ArmorDescriptorRear>
    <ArmorDescriptorTop>202 : 63132 (True) - TArmorDescriptor</ArmorDescriptorTop>
  </TBlindageProperties>
  <TBlindageProperties id="49317">
    <ArmorDescriptorFront>202 : 65230 (True) - TArmorDescriptor</ArmorDescriptorFront>
    <ArmorDescriptorSides>202 : 63234 (True) - TArmorDescriptor</ArmorDescriptorSides>
    <ArmorDescriptorRear>202 : 63132 (True) - TArmorDescriptor</ArmorDescriptorRear>
    <ArmorDescriptorTop>202 : 62962 (True) - TArmorDescriptor</ArmorDescriptorTop>
  </TBlindageProperties>
  <TBlindageProperties id="49385">
    <ArmorDescriptorFront>202 : 62962 (True) - TArmorDescriptor</ArmorDescriptorFront>
    <ArmorDescriptorSides>202 : 62962 (True) - TArmorDescriptor</ArmorDescriptorSides>
    <ArmorDescriptorRear>202 : 62898 (True) - TArmorDescriptor</ArmorDescriptorRear>
    <ArmorDescriptorTop>202 : 62898 (True) - TArmorDescriptor</ArmorDescriptorTop>
  </TBlindageProperties>
  <TBlindageProperties id="49552">
    <ArmorDescriptorFront>202 : 63271 (True) - TArmorDescriptor</ArmorDescriptorFront>
    <ArmorDescriptorSides>202 : 63234 (True) - TArmorDescriptor</ArmorDescriptorSides>
    <ArmorDescriptorRear>202 : 62962 (True) - TArmorDescriptor</ArmorDescriptorRear>
    <ArmorDescriptorTop>202 : 62962 (True) - TArmorDescriptor</ArmorDescriptorTop>
  </TBlindageProperties>
  <TBlindageProperties id="49572">
    <ArmorDescriptorFront>202 : 64038 (True) - TArmorDescriptor</ArmorDescriptorFront>
    <ArmorDescriptorSides>202 : 63132 (True) - TArmorDescriptor</ArmorDescriptorSides>
    <ArmorDescriptorRear>202 : 62962 (True) - TArmorDescriptor</ArmorDescriptorRear>
    <ArmorDescriptorTop>202 : 62898 (True) - TArmorDescriptor</ArmorDescriptorTop>
  </TBlindageProperties>
  <TBlindageProperties id="49628">
    <ArmorDescriptorFront>202 : 63132 (True) - TArmorDescriptor</ArmorDescriptorFront>
    <ArmorDescriptorSides>202 : 62898 (True) - TArmorDescriptor</ArmorDescriptorSides>
    <ArmorDescriptorRear>202 : 62899 (True) - TArmorDescriptor</ArmorDescriptorRear>
    <ArmorDescriptorTop>202 : 63011 (True) - TArmorDescriptor</ArmorDescriptorTop>
  </TBlindageProperties>
  <TBlindageProperties id="49720">
    <ArmorDescriptorFront>202 : 63265 (True) - TArmorDescriptor</ArmorDescriptorFront>
    <ArmorDescriptorSides>202 : 62961 (True) - TArmorDescriptor</ArmorDescriptorSides>
    <ArmorDescriptorRear>202 : 62898 (True) - TArmorDescriptor</ArmorDescriptorRear>
    <ArmorDescriptorTop>202 : 62898 (True) - TArmorDescriptor</ArmorDescriptorTop>
  </TBlindageProperties>
  <TBlindageProperties id="49751">
    <ArmorDescriptorFront>202 : 63271 (True) - TArmorDescriptor</ArmorDescriptorFront>
    <ArmorDescriptorSides>202 : 63234 (True) - TArmorDescriptor</ArmorDescriptorSides>
    <ArmorDescriptorRear>202 : 62962 (True) - TArmorDescriptor</ArmorDescriptorRear>
    <ArmorDescriptorTop>202 : 62898 (True) - TArmorDescriptor</ArmorDescriptorTop>
  </TBlindageProperties>
  <TBlindageProperties id="49764">
    <ArmorDescriptorFront>202 : 64074 (True) - TArmorDescriptor</ArmorDescriptorFront>
    <ArmorDescriptorSides>202 : 63234 (True) - TArmorDescriptor</ArmorDescriptorSides>
    <ArmorDescriptorRear>202 : 62962 (True) - TArmorDescriptor</ArmorDescriptorRear>
    <ArmorDescriptorTop>202 : 62898 (True) - TArmorDescriptor</ArmorDescriptorTop>
  </TBlindageProperties>
  <TBlindageProperties id="50050">
    <ArmorDescriptorFront>202 : 65649 (True) - TArmorDescriptor</ArmorDescriptorFront>
    <ArmorDescriptorSides>202 : 63234 (True) - TArmorDescriptor</ArmorDescriptorSides>
    <ArmorDescriptorRear>202 : 62962 (True) - TArmorDescriptor</ArmorDescriptorRear>
    <ArmorDescriptorTop>202 : 62962 (True) - TArmorDescriptor</ArmorDescriptorTop>
  </TBlindageProperties>
  <TBlindageProperties id="50092">
    <ArmorDescriptorFront>202 : 62961 (True) - TArmorDescriptor</ArmorDescriptorFront>
    <ArmorDescriptorSides>202 : 62898 (True) - TArmorDescriptor</ArmorDescriptorSides>
    <ArmorDescriptorRear>202 : 62898 (True) - TArmorDescriptor</ArmorDescriptorRear>
    <ArmorDescriptorTop>202 : 62899 (True) - TArmorDescriptor</ArmorDescriptorTop>
  </TBlindageProperties>
  <TBlindageProperties id="50103">
    <ArmorDescriptorFront>202 : 63226 (True) - TArmorDescriptor</ArmorDescriptorFront>
    <ArmorDescriptorSides>202 : 62898 (True) - TArmorDescriptor</ArmorDescriptorSides>
    <ArmorDescriptorRear>202 : 62898 (True) - TArmorDescriptor</ArmorDescriptorRear>
    <ArmorDescriptorTop>202 : 62899 (True) - TArmorDescriptor</ArmorDescriptorTop>
  </TBlindageProperties>
  <TBlindageProperties id="50134">
    <ArmorDescriptorFront>202 : 63265 (True) - TArmorDescriptor</ArmorDescriptorFront>
    <ArmorDescriptorSides>202 : 62962 (True) - TArmorDescriptor</ArmorDescriptorSides>
    <ArmorDescriptorRear>202 : 62898 (True) - TArmorDescriptor</ArmorDescriptorRear>
    <ArmorDescriptorTop>202 : 62898 (True) - TArmorDescriptor</ArmorDescriptorTop>
  </TBlindageProperties>
  <TBlindageProperties id="50145">
    <ArmorDescriptorFront>202 : 63667 (True) - TArmorDescriptor</ArmorDescriptorFront>
    <ArmorDescriptorSides>202 : 62961 (True) - TArmorDescriptor</ArmorDescriptorSides>
    <ArmorDescriptorRear>202 : 63132 (True) - TArmorDescriptor</ArmorDescriptorRear>
    <ArmorDescriptorTop>202 : 62962 (True) - TArmorDescriptor</ArmorDescriptorTop>
  </TBlindageProperties>
  <TBlindageProperties id="50156">
    <ArmorDescriptorFront>202 : 65708 (True) - TArmorDescriptor</ArmorDescriptorFront>
    <ArmorDescriptorSides>202 : 63234 (True) - TArmorDescriptor</ArmorDescriptorSides>
    <ArmorDescriptorRear>202 : 63132 (True) - TArmorDescriptor</ArmorDescriptorRear>
    <ArmorDescriptorTop>202 : 62962 (True) - TArmorDescriptor</ArmorDescriptorTop>
  </TBlindageProperties>
  <TBlindageProperties id="50167">
    <ArmorDescriptorFront>202 : 64413 (True) - TArmorDescriptor</ArmorDescriptorFront>
    <ArmorDescriptorSides>202 : 64038 (True) - TArmorDescriptor</ArmorDescriptorSides>
    <ArmorDescriptorRear>202 : 63132 (True) - TArmorDescriptor</ArmorDescriptorRear>
    <ArmorDescriptorTop>202 : 62962 (True) - TArmorDescriptor</ArmorDescriptorTop>
  </TBlindageProperties>
  <TBlindageProperties id="50238">
    <ArmorDescriptorFront>202 : 65747 (True) - TArmorDescriptor</ArmorDescriptorFront>
    <ArmorDescriptorSides>202 : 64038 (True) - TArmorDescriptor</ArmorDescriptorSides>
    <ArmorDescriptorRear>202 : 63132 (True) - TArmorDescriptor</ArmorDescriptorRear>
    <ArmorDescriptorTop>202 : 62962 (True) - TArmorDescriptor</ArmorDescriptorTop>
  </TBlindageProperties>
  <TBlindageProperties id="50269">
    <ArmorDescriptorFront>202 : 63271 (True) - TArmorDescriptor</ArmorDescriptorFront>
    <ArmorDescriptorSides>202 : 62962 (True) - TArmorDescriptor</ArmorDescriptorSides>
    <ArmorDescriptorRear>202 : 62898 (True) - TArmorDescriptor</ArmorDescriptorRear>
    <ArmorDescriptorTop>202 : 62898 (True) - TArmorDescriptor</ArmorDescriptorTop>
  </TBlindageProperties>
  <TBlindageProperties id="50280">
    <ArmorDescriptorFront>202 : 63668 (True) - TArmorDescriptor</ArmorDescriptorFront>
    <ArmorDescriptorSides>202 : 62898 (True) - TArmorDescriptor</ArmorDescriptorSides>
    <ArmorDescriptorRear>202 : 62898 (True) - TArmorDescriptor</ArmorDescriptorRear>
    <ArmorDescriptorTop>202 : 62899 (True) - TArmorDescriptor</ArmorDescriptorTop>
  </TBlindageProperties>
  <TBlindageProperties id="51039">
    <ArmorDescriptorFront>202 : 64306 (True) - TArmorDescriptor</ArmorDescriptorFront>
    <ArmorDescriptorSides>202 : 63668 (True) - TArmorDescriptor</ArmorDescriptorSides>
    <ArmorDescriptorRear>202 : 63132 (True) - TArmorDescriptor</ArmorDescriptorRear>
    <ArmorDescriptorTop>202 : 63132 (True) - TArmorDescriptor</ArmorDescriptorTop>
  </TBlindageProperties>
  <TBlindageProperties id="51073">
    <ArmorDescriptorFront>202 : 65747 (True) - TArmorDescriptor</ArmorDescriptorFront>
    <ArmorDescriptorSides>202 : 64038 (True) - TArmorDescriptor</ArmorDescriptorSides>
    <ArmorDescriptorRear>202 : 62961 (True) - TArmorDescriptor</ArmorDescriptorRear>
    <ArmorDescriptorTop>202 : 63132 (True) - TArmorDescriptor</ArmorDescriptorTop>
  </TBlindageProperties>
  <TBlindageProperties id="51085">
    <ArmorDescriptorFront>202 : 65230 (True) - TArmorDescriptor</ArmorDescriptorFront>
    <ArmorDescriptorSides>202 : 63234 (True) - TArmorDescriptor</ArmorDescriptorSides>
    <ArmorDescriptorRear>202 : 62962 (True) - TArmorDescriptor</ArmorDescriptorRear>
    <ArmorDescriptorTop>202 : 62962 (True) - TArmorDescriptor</ArmorDescriptorTop>
  </TBlindageProperties>
  <TBlindageProperties id="51097">
    <ArmorDescriptorFront>202 : 63667 (True) - TArmorDescriptor</ArmorDescriptorFront>
    <ArmorDescriptorSides>202 : 63226 (True) - TArmorDescriptor</ArmorDescriptorSides>
    <ArmorDescriptorRear>202 : 62962 (True) - TArmorDescriptor</ArmorDescriptorRear>
    <ArmorDescriptorTop>202 : 62962 (True) - TArmorDescriptor</ArmorDescriptorTop>
  </TBlindageProperties>
  <TBlindageProperties id="51382">
    <ArmorDescriptorFront>202 : 62961 (True) - TArmorDescriptor</ArmorDescriptorFront>
    <ArmorDescriptorSides>202 : 63132 (True) - TArmorDescriptor</ArmorDescriptorSides>
    <ArmorDescriptorRear>202 : 62899 (True) - TArmorDescriptor</ArmorDescriptorRear>
    <ArmorDescriptorTop>202 : 62899 (True) - TArmorDescriptor</ArmorDescriptorTop>
  </TBlindageProperties>
  <TBlindageProperties id="51393">
    <ArmorDescriptorFront>202 : 63226 (True) - TArmorDescriptor</ArmorDescriptorFront>
    <ArmorDescriptorSides>202 : 62962 (True) - TArmorDescriptor</ArmorDescriptorSides>
    <ArmorDescriptorRear>202 : 62899 (True) - TArmorDescriptor</ArmorDescriptorRear>
    <ArmorDescriptorTop>202 : 62899 (True) - TArmorDescriptor</ArmorDescriptorTop>
  </TBlindageProperties>
  <TBlindageProperties id="51466">
    <ArmorDescriptorFront>202 : 62898 (True) - TArmorDescriptor</ArmorDescriptorFront>
    <ArmorDescriptorSides>202 : 62898 (True) - TArmorDescriptor</ArmorDescriptorSides>
    <ArmorDescriptorRear>202 : 62898 (True) - TArmorDescriptor</ArmorDescriptorRear>
    <ArmorDescriptorTop>202 : 62899 (True) - TArmorDescriptor</ArmorDescriptorTop>
  </TBlindageProperties>
  <TBlindageProperties id="51544">
    <ArmorDescriptorFront>202 : 63271 (True) - TArmorDescriptor</ArmorDescriptorFront>
    <ArmorDescriptorSides>202 : 62961 (True) - TArmorDescriptor</ArmorDescriptorSides>
    <ArmorDescriptorRear>202 : 62962 (True) - TArmorDescriptor</ArmorDescriptorRear>
    <ArmorDescriptorTop>202 : 62898 (True) - TArmorDescriptor</ArmorDescriptorTop>
  </TBlindageProperties>
  <TBlindageProperties id="51578">
    <ArmorDescriptorFront>202 : 63265 (True) - TArmorDescriptor</ArmorDescriptorFront>
    <ArmorDescriptorSides>202 : 63132 (True) - TArmorDescriptor</ArmorDescriptorSides>
    <ArmorDescriptorRear>202 : 62898 (True) - TArmorDescriptor</ArmorDescriptorRear>
    <ArmorDescriptorTop>202 : 62898 (True) - TArmorDescriptor</ArmorDescriptorTop>
  </TBlindageProperties>
  <TBlindageProperties id="51610">
    <ArmorDescriptorFront>202 : 66431 (True) - TArmorDescriptor</ArmorDescriptorFront>
    <ArmorDescriptorSides>202 : 63668 (True) - TArmorDescriptor</ArmorDescriptorSides>
    <ArmorDescriptorRear>202 : 63132 (True) - TArmorDescriptor</ArmorDescriptorRear>
    <ArmorDescriptorTop>202 : 62962 (True) - TArmorDescriptor</ArmorDescriptorTop>
  </TBlindageProperties>
  <TBlindageProperties id="51736">
    <ArmorDescriptorFront>202 : 66431 (True) - TArmorDescriptor</ArmorDescriptorFront>
    <ArmorDescriptorSides>202 : 62962 (True) - TArmorDescriptor</ArmorDescriptorSides>
    <ArmorDescriptorRear>202 : 62898 (True) - TArmorDescriptor</ArmorDescriptorRear>
    <ArmorDescriptorTop>202 : 62898 (True) - TArmorDescriptor</ArmorDescriptorTop>
  </TBlindageProperties>
  <TBlindageProperties id="51856">
    <ArmorDescriptorFront>202 : 63271 (True) - TArmorDescriptor</ArmorDescriptorFront>
    <ArmorDescriptorSides>202 : 63226 (True) - TArmorDescriptor</ArmorDescriptorSides>
    <ArmorDescriptorRear>202 : 62962 (True) - TArmorDescriptor</ArmorDescriptorRear>
    <ArmorDescriptorTop>202 : 62962 (True) - TArmorDescriptor</ArmorDescriptorTop>
  </TBlindageProperties>
  <TBlindageProperties id="52073">
    <ArmorDescriptorFront>202 : 63265 (True) - TArmorDescriptor</ArmorDescriptorFront>
    <ArmorDescriptorSides>202 : 62961 (True) - TArmorDescriptor</ArmorDescriptorSides>
    <ArmorDescriptorRear>202 : 63132 (True) - TArmorDescriptor</ArmorDescriptorRear>
    <ArmorDescriptorTop>202 : 62898 (True) - TArmorDescriptor</ArmorDescriptorTop>
  </TBlindageProperties>
  <TBlindageProperties id="52082">
    <ArmorDescriptorFront>202 : 62898 (True) - TArmorDescriptor</ArmorDescriptorFront>
    <ArmorDescriptorSides>202 : 62898 (True) - TArmorDescriptor</ArmorDescriptorSides>
    <ArmorDescriptorRear>202 : 62899 (True) - TArmorDescriptor</ArmorDescriptorRear>
    <ArmorDescriptorTop>202 : 62898 (True) - TArmorDescriptor</ArmorDescriptorTop>
  </TBlindageProperties>
  <TBlindageProperties id="52498">
    <ArmorDescriptorFront>202 : 62962 (True) - TArmorDescriptor</ArmorDescriptorFront>
    <ArmorDescriptorSides>202 : 62898 (True) - TArmorDescriptor</ArmorDescriptorSides>
    <ArmorDescriptorRear>202 : 62898 (True) - TArmorDescriptor</ArmorDescriptorRear>
    <ArmorDescriptorTop>202 : 62898 (True) - TArmorDescriptor</ArmorDescriptorTop>
  </TBlindageProperties>
  <TBlindageProperties id="52668">
    <ArmorDescriptorFront>202 : 64306 (True) - TArmorDescriptor</ArmorDescriptorFront>
    <ArmorDescriptorSides>202 : 63265 (True) - TArmorDescriptor</ArmorDescriptorSides>
    <ArmorDescriptorRear>202 : 63132 (True) - TArmorDescriptor</ArmorDescriptorRear>
    <ArmorDescriptorTop>202 : 63132 (True) - TArmorDescriptor</ArmorDescriptorTop>
  </TBlindageProperties>
  <TBlindageProperties id="53716">
    <ArmorDescriptorFront>202 : 63132 (True) - TArmorDescriptor</ArmorDescriptorFront>
    <ArmorDescriptorSides>202 : 62898 (True) - TArmorDescriptor</ArmorDescriptorSides>
    <ArmorDescriptorRear>202 : 62898 (True) - TArmorDescriptor</ArmorDescriptorRear>
    <ArmorDescriptorTop>202 : 62899 (True) - TArmorDescriptor</ArmorDescriptorTop>
  </TBlindageProperties>
  <TBlindageProperties id="54160">
    <ArmorDescriptorFront>202 : 66431 (True) - TArmorDescriptor</ArmorDescriptorFront>
    <ArmorDescriptorSides>202 : 62961 (True) - TArmorDescriptor</ArmorDescriptorSides>
    <ArmorDescriptorRear>202 : 62962 (True) - TArmorDescriptor</ArmorDescriptorRear>
    <ArmorDescriptorTop>202 : 62898 (True) - TArmorDescriptor</ArmorDescriptorTop>
  </TBlindageProperties>
  <TBlindageProperties id="54218">
    <ArmorDescriptorFront>202 : 63265 (True) - TArmorDescriptor</ArmorDescriptorFront>
    <ArmorDescriptorSides>202 : 63226 (True) - TArmorDescriptor</ArmorDescriptorSides>
    <ArmorDescriptorRear>202 : 62962 (True) - TArmorDescriptor</ArmorDescriptorRear>
    <ArmorDescriptorTop>202 : 62898 (True) - TArmorDescriptor</ArmorDescriptorTop>
  </TBlindageProperties>
  <TBlindageProperties id="54402">
    <ArmorDescriptorFront>202 : 66431 (True) - TArmorDescriptor</ArmorDescriptorFront>
    <ArmorDescriptorSides>202 : 63226 (True) - TArmorDescriptor</ArmorDescriptorSides>
    <ArmorDescriptorRear>202 : 62962 (True) - TArmorDescriptor</ArmorDescriptorRear>
    <ArmorDescriptorTop>202 : 62962 (True) - TArmorDescriptor</ArmorDescriptorTop>
  </TBlindageProperties>
  <TBlindageProperties id="54546">
    <ArmorDescriptorFront>202 : 66431 (True) - TArmorDescriptor</ArmorDescriptorFront>
    <ArmorDescriptorSides>202 : 63226 (True) - TArmorDescriptor</ArmorDescriptorSides>
    <ArmorDescriptorRear>202 : 62962 (True) - TArmorDescriptor</ArmorDescriptorRear>
    <ArmorDescriptorTop>202 : 62898 (True) - TArmorDescriptor</ArmorDescriptorTop>
  </TBlindageProperties>
  <TBlindageProperties id="54557">
    <ArmorDescriptorFront>202 : 65230 (True) - TArmorDescriptor</ArmorDescriptorFront>
    <ArmorDescriptorSides>202 : 63668 (True) - TArmorDescriptor</ArmorDescriptorSides>
    <ArmorDescriptorRear>202 : 63132 (True) - TArmorDescriptor</ArmorDescriptorRear>
    <ArmorDescriptorTop>202 : 62962 (True) - TArmorDescriptor</ArmorDescriptorTop>
  </TBlindageProperties>
  <TBlindageProperties id="54569">
    <ArmorDescriptorFront>202 : 65708 (True) - TArmorDescriptor</ArmorDescriptorFront>
    <ArmorDescriptorSides>202 : 63234 (True) - TArmorDescriptor</ArmorDescriptorSides>
    <ArmorDescriptorRear>202 : 62962 (True) - TArmorDescriptor</ArmorDescriptorRear>
    <ArmorDescriptorTop>202 : 62962 (True) - TArmorDescriptor</ArmorDescriptorTop>
  </TBlindageProperties>
  <TBlindageProperties id="54601">
    <ArmorDescriptorFront>202 : 66431 (True) - TArmorDescriptor</ArmorDescriptorFront>
    <ArmorDescriptorSides>202 : 63234 (True) - TArmorDescriptor</ArmorDescriptorSides>
    <ArmorDescriptorRear>202 : 62962 (True) - TArmorDescriptor</ArmorDescriptorRear>
    <ArmorDescriptorTop>202 : 62898 (True) - TArmorDescriptor</ArmorDescriptorTop>
  </TBlindageProperties>
  <TBlindageProperties id="54626">
    <ArmorDescriptorFront>202 : 63667 (True) - TArmorDescriptor</ArmorDescriptorFront>
    <ArmorDescriptorSides>202 : 63668 (True) - TArmorDescriptor</ArmorDescriptorSides>
    <ArmorDescriptorRear>202 : 63132 (True) - TArmorDescriptor</ArmorDescriptorRear>
    <ArmorDescriptorTop>202 : 63132 (True) - TArmorDescriptor</ArmorDescriptorTop>
  </TBlindageProperties>
  <TBlindageProperties id="54644">
    <ArmorDescriptorFront>202 : 65223 (True) - TArmorDescriptor</ArmorDescriptorFront>
    <ArmorDescriptorSides>202 : 64038 (True) - TArmorDescriptor</ArmorDescriptorSides>
    <ArmorDescriptorRear>202 : 63132 (True) - TArmorDescriptor</ArmorDescriptorRear>
    <ArmorDescriptorTop>202 : 63132 (True) - TArmorDescriptor</ArmorDescriptorTop>
  </TBlindageProperties>
  <TBlindageProperties id="54656">
    <ArmorDescriptorFront>202 : 64306 (True) - TArmorDescriptor</ArmorDescriptorFront>
    <ArmorDescriptorSides>202 : 63265 (True) - TArmorDescriptor</ArmorDescriptorSides>
    <ArmorDescriptorRear>202 : 62961 (True) - TArmorDescriptor</ArmorDescriptorRear>
    <ArmorDescriptorTop>202 : 63132 (True) - TArmorDescriptor</ArmorDescriptorTop>
  </TBlindageProperties>
  <TBlindageProperties id="54718">
    <ArmorDescriptorFront>202 : 65230 (True) - TArmorDescriptor</ArmorDescriptorFront>
    <ArmorDescriptorSides>202 : 64038 (True) - TArmorDescriptor</ArmorDescriptorSides>
    <ArmorDescriptorRear>202 : 63132 (True) - TArmorDescriptor</ArmorDescriptorRear>
    <ArmorDescriptorTop>202 : 63132 (True) - TArmorDescriptor</ArmorDescriptorTop>
  </TBlindageProperties>
  <TBlindageProperties id="54729">
    <ArmorDescriptorFront>202 : 65223 (True) - TArmorDescriptor</ArmorDescriptorFront>
    <ArmorDescriptorSides>202 : 63668 (True) - TArmorDescriptor</ArmorDescriptorSides>
    <ArmorDescriptorRear>202 : 63132 (True) - TArmorDescriptor</ArmorDescriptorRear>
    <ArmorDescriptorTop>202 : 63132 (True) - TArmorDescriptor</ArmorDescriptorTop>
  </TBlindageProperties>
  <TBlindageProperties id="54777">
    <ArmorDescriptorFront>202 : 65649 (True) - TArmorDescriptor</ArmorDescriptorFront>
    <ArmorDescriptorSides>202 : 63265 (True) - TArmorDescriptor</ArmorDescriptorSides>
    <ArmorDescriptorRear>202 : 62961 (True) - TArmorDescriptor</ArmorDescriptorRear>
    <ArmorDescriptorTop>202 : 63132 (True) - TArmorDescriptor</ArmorDescriptorTop>
  </TBlindageProperties>
  <TBlindageProperties id="54788">
    <ArmorDescriptorFront>202 : 63667 (True) - TArmorDescriptor</ArmorDescriptorFront>
    <ArmorDescriptorSides>202 : 64038 (True) - TArmorDescriptor</ArmorDescriptorSides>
    <ArmorDescriptorRear>202 : 63132 (True) - TArmorDescriptor</ArmorDescriptorRear>
    <ArmorDescriptorTop>202 : 63132 (True) - TArmorDescriptor</ArmorDescriptorTop>
  </TBlindageProperties>
  <TBlindageProperties id="54799">
    <ArmorDescriptorFront>202 : 66431 (True) - TArmorDescriptor</ArmorDescriptorFront>
    <ArmorDescriptorSides>202 : 63668 (True) - TArmorDescriptor</ArmorDescriptorSides>
    <ArmorDescriptorRear>202 : 62962 (True) - TArmorDescriptor</ArmorDescriptorRear>
    <ArmorDescriptorTop>202 : 62962 (True) - TArmorDescriptor</ArmorDescriptorTop>
  </TBlindageProperties>
  <TBlindageProperties id="54811">
    <ArmorDescriptorFront>202 : 65708 (True) - TArmorDescriptor</ArmorDescriptorFront>
    <ArmorDescriptorSides>202 : 63265 (True) - TArmorDescriptor</ArmorDescriptorSides>
    <ArmorDescriptorRear>202 : 63132 (True) - TArmorDescriptor</ArmorDescriptorRear>
    <ArmorDescriptorTop>202 : 62962 (True) - TArmorDescriptor</ArmorDescriptorTop>
  </TBlindageProperties>
  <TBlindageProperties id="54823">
    <ArmorDescriptorFront>202 : 64074 (True) - TArmorDescriptor</ArmorDescriptorFront>
    <ArmorDescriptorSides>202 : 63668 (True) - TArmorDescriptor</ArmorDescriptorSides>
    <ArmorDescriptorRear>202 : 62962 (True) - TArmorDescriptor</ArmorDescriptorRear>
    <ArmorDescriptorTop>202 : 62962 (True) - TArmorDescriptor</ArmorDescriptorTop>
  </TBlindageProperties>
  <TBlindageProperties id="54835">
    <ArmorDescriptorFront>202 : 65230 (True) - TArmorDescriptor</ArmorDescriptorFront>
    <ArmorDescriptorSides>202 : 64038 (True) - TArmorDescriptor</ArmorDescriptorSides>
    <ArmorDescriptorRear>202 : 62962 (True) - TArmorDescriptor</ArmorDescriptorRear>
    <ArmorDescriptorTop>202 : 62962 (True) - TArmorDescriptor</ArmorDescriptorTop>
  </TBlindageProperties>
  <TBlindageProperties id="54889">
    <ArmorDescriptorFront>202 : 65747 (True) - TArmorDescriptor</ArmorDescriptorFront>
    <ArmorDescriptorSides>202 : 63265 (True) - TArmorDescriptor</ArmorDescriptorSides>
    <ArmorDescriptorRear>202 : 62961 (True) - TArmorDescriptor</ArmorDescriptorRear>
    <ArmorDescriptorTop>202 : 63132 (True) - TArmorDescriptor</ArmorDescriptorTop>
  </TBlindageProperties>
  <TBlindageProperties id="55300">
    <ArmorDescriptorFront>202 : 62962 (True) - TArmorDescriptor</ArmorDescriptorFront>
    <ArmorDescriptorSides>202 : 62898 (True) - TArmorDescriptor</ArmorDescriptorSides>
    <ArmorDescriptorRear>202 : 62899 (True) - TArmorDescriptor</ArmorDescriptorRear>
    <ArmorDescriptorTop>202 : 63011 (True) - TArmorDescriptor</ArmorDescriptorTop>
  </TBlindageProperties>
  <TBlindageProperties id="55410">
    <ArmorDescriptorFront>202 : 63668 (True) - TArmorDescriptor</ArmorDescriptorFront>
    <ArmorDescriptorSides>202 : 63132 (True) - TArmorDescriptor</ArmorDescriptorSides>
    <ArmorDescriptorRear>202 : 62899 (True) - TArmorDescriptor</ArmorDescriptorRear>
    <ArmorDescriptorTop>202 : 62899 (True) - TArmorDescriptor</ArmorDescriptorTop>
  </TBlindageProperties>
  <TBlindageProperties id="55518">
    <ArmorDescriptorFront>202 : 63226 (True) - TArmorDescriptor</ArmorDescriptorFront>
    <ArmorDescriptorSides>202 : 62962 (True) - TArmorDescriptor</ArmorDescriptorSides>
    <ArmorDescriptorRear>202 : 62898 (True) - TArmorDescriptor</ArmorDescriptorRear>
    <ArmorDescriptorTop>202 : 63011 (True) - TArmorDescriptor</ArmorDescriptorTop>
  </TBlindageProperties>
  <TBlindageProperties id="55592">
    <ArmorDescriptorFront>202 : 64074 (True) - TArmorDescriptor</ArmorDescriptorFront>
    <ArmorDescriptorSides>202 : 63234 (True) - TArmorDescriptor</ArmorDescriptorSides>
    <ArmorDescriptorRear>202 : 62898 (True) - TArmorDescriptor</ArmorDescriptorRear>
    <ArmorDescriptorTop>202 : 62898 (True) - TArmorDescriptor</ArmorDescriptorTop>
  </TBlindageProperties>
  <TBlindageProperties id="55603">
    <ArmorDescriptorFront>202 : 64413 (True) - TArmorDescriptor</ArmorDescriptorFront>
    <ArmorDescriptorSides>202 : 63234 (True) - TArmorDescriptor</ArmorDescriptorSides>
    <ArmorDescriptorRear>202 : 62962 (True) - TArmorDescriptor</ArmorDescriptorRear>
    <ArmorDescriptorTop>202 : 62962 (True) - TArmorDescriptor</ArmorDescriptorTop>
  </TBlindageProperties>
  <TBlindageProperties id="55614">
    <ArmorDescriptorFront>202 : 63271 (True) - TArmorDescriptor</ArmorDescriptorFront>
    <ArmorDescriptorSides>202 : 62961 (True) - TArmorDescriptor</ArmorDescriptorSides>
    <ArmorDescriptorRear>202 : 62898 (True) - TArmorDescriptor</ArmorDescriptorRear>
    <ArmorDescriptorTop>202 : 62898 (True) - TArmorDescriptor</ArmorDescriptorTop>
  </TBlindageProperties>
  <TBlindageProperties id="55677">
    <ArmorDescriptorFront>202 : 63132 (True) - TArmorDescriptor</ArmorDescriptorFront>
    <ArmorDescriptorSides>202 : 62962 (True) - TArmorDescriptor</ArmorDescriptorSides>
    <ArmorDescriptorRear>202 : 62898 (True) - TArmorDescriptor</ArmorDescriptorRear>
    <ArmorDescriptorTop>202 : 62899 (True) - TArmorDescriptor</ArmorDescriptorTop>
  </TBlindageProperties>
  <TBlindageProperties id="56310">
    <ArmorDescriptorFront>202 : 63132 (True) - TArmorDescriptor</ArmorDescriptorFront>
    <ArmorDescriptorSides>202 : 62898 (True) - TArmorDescriptor</ArmorDescriptorSides>
    <ArmorDescriptorRear>202 : 62898 (True) - TArmorDescriptor</ArmorDescriptorRear>
    <ArmorDescriptorTop>202 : 62898 (True) - TArmorDescriptor</ArmorDescriptorTop>
  </TBlindageProperties>
  <TBlindageProperties id="57001">
    <ArmorDescriptorFront>202 : 63132 (True) - TArmorDescriptor</ArmorDescriptorFront>
    <ArmorDescriptorSides>202 : 62899 (True) - TArmorDescriptor</ArmorDescriptorSides>
    <ArmorDescriptorRear>202 : 63132 (True) - TArmorDescriptor</ArmorDescriptorRear>
    <ArmorDescriptorTop>202 : 63011 (True) - TArmorDescriptor</ArmorDescriptorTop>
  </TBlindageProperties>
  <TBlindageProperties id="57039">
    <ArmorDescriptorFront>202 : 62898 (True) - TArmorDescriptor</ArmorDescriptorFront>
    <ArmorDescriptorSides>202 : 62898 (True) - TArmorDescriptor</ArmorDescriptorSides>
    <ArmorDescriptorRear>202 : 62898 (True) - TArmorDescriptor</ArmorDescriptorRear>
    <ArmorDescriptorTop>202 : 63011 (True) - TArmorDescriptor</ArmorDescriptorTop>
  </TBlindageProperties>
  <TBlindageProperties id="57088">
    <ArmorDescriptorFront>202 : 63132 (True) - TArmorDescriptor</ArmorDescriptorFront>
    <ArmorDescriptorSides>202 : 62898 (True) - TArmorDescriptor</ArmorDescriptorSides>
    <ArmorDescriptorRear>202 : 63132 (True) - TArmorDescriptor</ArmorDescriptorRear>
    <ArmorDescriptorTop>202 : 63011 (True) - TArmorDescriptor</ArmorDescriptorTop>
  </TBlindageProperties>
  <TBlindageProperties id="59749">
    <ArmorDescriptorFront>202 : 62898 (True) - TArmorDescriptor</ArmorDescriptorFront>
    <ArmorDescriptorSides>202 : 62899 (True) - TArmorDescriptor</ArmorDescriptorSides>
    <ArmorDescriptorRear>202 : 62898 (True) - TArmorDescriptor</ArmorDescriptorRear>
    <ArmorDescriptorTop>202 : 62899 (True) - TArmorDescriptor</ArmorDescriptorTop>
  </TBlindageProperties>
  <TBlindageProperties id="59769">
    <ArmorDescriptorFront>202 : 70886 (True) - TArmorDescriptor</ArmorDescriptorFront>
    <ArmorDescriptorSides>202 : 70886 (True) - TArmorDescriptor</ArmorDescriptorSides>
    <ArmorDescriptorRear>202 : 70886 (True) - TArmorDescriptor</ArmorDescriptorRear>
    <ArmorDescriptorTop>202 : 70886 (True) - TArmorDescriptor</ArmorDescriptorTop>
  </TBlindageProperties>
  <TBlindageProperties id="62809">
    <ArmorDescriptorFront>202 : 73063 (True) - TArmorDescriptor</ArmorDescriptorFront>
    <ArmorDescriptorSides>202 : 73063 (True) - TArmorDescriptor</ArmorDescriptorSides>
    <ArmorDescriptorRear>202 : 73063 (True) - TArmorDescriptor</ArmorDescriptorRear>
    <ArmorDescriptorTop>202 : 73063 (True) - TArmorDescriptor</ArmorDescriptorTop>
  </TBlindageProperties>
</TBlindagePropertiess>